Workbook
Name arrêt_prévu__sans_prol: [1]evo_reacteur!$D$1:$D$121
Name Base: #REF!
Name Base3: [2]REACTORSWNISR2019!$A$1:$BD$789
Name Col_Age: [2]REACTORSWNISR2019!$AP$2:$AP$1048576
Name col_consCanc: [2]DATA_CancSusp!$F:$F
Name col_consResume: [2]DATA_CancSusp!$I:$I
Name col_consSusp: [2]DATA_CancSusp!$H:$H
Name col_ConsYear_2018Plus: [2]REACTORSWNISR2019!$O:$O
Name Col_Country: [2]REACTORSWNISR2019!$D$2:$D$1048576
Name col_Country_2018Plus: [2]REACTORSWNISR2019!$D:$D
Name Col_OperatingAge: [2]REACTORSWNISR2019!$AN$2:$AN$1048576
Name Col_Region_2018Plus: [2]REACTORSWNISR2019!$C:$C
Name Col_ShutAge: [2]REACTORSWNISR2019!$AQ:$AQ
Name col_ShutDownYear: [2]REACTORSWNISR2019!$AA:$AA
Name Col_StartUpYear_2018Plus: [2]REACTORSWNISR2019!$X:$X
Name Col_Status_2018Plus: [2]REACTORSWNISR2019!$F:$F
Name ConstructionCanc_Susp: [2]DATA_CancSusp!$A$4:$I$110
Name Country: [3]codes!$D$3:$D$38
Name GEO: [3]codes!$A$2:$A$9
Name OCC_COL: 'Specific OCC in $ per kW 2018 '!$S:$S
Name Reactors_Years_IAEA2021: [2]DATAReactors_Years!$AJ:$AJ
Name Reactors_Years_Reference_unit_power: [2]DATAReactors_Years!$AN:$AN
Name Reactors_Years_WNISR2021: [2]DATAReactors_Years!$V:$V
Name Reactors_Years_Year: [2]DATAReactors_Years!$F:$F
Name Reactors_Years2_Country: [2]DATAReactors_Years2021!$C:$C
Name Reactors_Years2_Reference_unit_power: [2]DATAReactors_Years2021!$AN:$AN
Name Reactors_Years2_WNISR2022: [2]DATAReactors_Years2021!$V:$V
Name Reactors_Years2_Year: [2]DATAReactors_Years2021!$F:$F
Name reactorssss: '[4]REACTORS.XLS'!$A$2:$BS$750
Name Tableau: #REF!

Sheet Table for Thesis
A2: Reactor | B2: Confinement Type | C2: Reactor Type | D2: Capacity [MW] | E2: Cost Type | F2: Readiness | G2: Relative/Absolute | H2: Value | I2: Unit | J2: Cost Reference Year | K2: Availability/Capacity Factor | L2: Comment | M2: Reference | N2: Operational Mode | O2: Contingency
A3: LIFE1 | B3: Inertia | C3: Indirect Drive | D3: 400 | E3: Capital Cost | F3: FOAK | G3: Absolute | H3: 6000000000 | I3: USD | J3: 2011 | K3: AV: 0.5 | L3: Learning rates based on experiences from NIF but not further specified | M3: Anklam et al. (2011) | N3: Steady-State (possible due to high repetition rate of laser pulses (nearly 15 per second)) | O3: -
A4: LIFE2 | B4: Inertia | C4: Indirect Drive | D4: 2200 | E4: Capital Cost | F4: NOAK | G4: Absolute | H4: 5000000000 | I4: USD | J4: 2011 | K4: AV: 0.92 | L4: Average value between 4 and 6 billion USD; Learning rates based on experiences from NIF but not further specified | M4: Anklam et al. (2011) | N4: Steady-State (possible due to high repetition rate of laser pulses (nearly 15 per second)) | O4: -
A5: LIFE3 | B5: Inertia | C5: Indirect Drive | D5: 2660 | E5: Capital Cost | F5: 10th-OAK | G5: Absolute | H5: 4000000000 | I5: USD | J5: 2011 | K5: AV: 0.92 | L5: Learning rates based on experiences from NIF but not further specified | M5: Anklam et al. (2011) | N5: Steady-State (possible due to high repetition rate of laser pulses (nearly 15 per second)) | O5: -
A6: UWMAK-III | B6: Magnetic | C6: Tokamak | D6: 1985 | E6: OCC | F6: 10th-OAK | G6: Absolute | H6: 3270000000 | I6: USD | J6: 1975 | K6: AV: 0.95 | M6: Badger et al. (1975) | N6: Pulsed but TES integrated for steady-state operation | O6: 980000000
A7: n.a. | B7: Magnetic | C7: Tokamak | D7: 1500 | E7: LCOE | F7: NOAK | G7: Relative | H7: 66.7 | I7: EUR/MWh | J7: 2011 | K7: AV: 0.8 | L7: Pessimistic scenario A; 40 years lifetime; 2060-2070; 10 years construction time | M7: Bednyagin & Gnansounou (2011)
A8: n.a. | B8: Magnetic | C8: Tokamak | D8: 1500 | E8: LCOE | F8: FOAK | G8: Relative | H8: 78.4 | I8: EUR/MWh | J8: 2011 | K8: CF: 0.8 | L8: Pessimistic scenario A; 40 years lifetime; 2060-2070; 10 years construction time | M8: Bednyagin & Gnansounou (2011) | N8: Steady-State | O8: -
A9: n.a. | B9: Magnetic | C9: Tokamak | D9: 1500 | E9: LCOE | F9: FOAK | G9: Relative | H9: 64.5 | I9: EUR/MWh | J9: 2011 | K9: CF: 0.8 | L9: Scenario B; 40 years litetim; 2050-2060; 10 years construction time | M9: Bednyagin & Gnansounou (2011) | N9: Steady-State | O9: -
A10: n.a. | B10: Magnetic | C10: Tokamak | D10: 1500 | E10: LCOE | F10: 10th-OAK | G10: Relative | H10: 61.1 | I10: EUR/MWh | J10: 2011 | K10: CF: 0.8 | L10: Pessimistic scenario A; 40 years lifetime; 2060-2070; 10 years construction time | M10: Bednyagin & Gnansounou (2011) | N10: Steady-State | O10: -
A11: n.a. | B11: Magnetic | C11: Tokamak | D11: 1500 | E11: LCOE | F11: 10th-OAK | G11: Relative | H11: 49.3 | I11: EUR/MWh | J11: 2011 | K11: CF: 0.8 | L11: Scenario B; 40 years litetim; 2050-2060; 10 years construction time | M11: Bednyagin & Gnansounou (2011) | N11: Steady-State | O11: -
A12: n.a. | B12: Magnetic | C12: Tokamak | D12: 1500 | E12: LCOE | F12: FOAK | G12: Relative | H12: 51.3 | I12: EUR/MWh | J12: 2011 | K12: CF: 0.8 | L12: Optimistic scenario C; 40 years litetim; 2050-2060; 10 years construction time | M12: Bednyagin & Gnansounou (2011) | N12: Steady-State | O12: -
A13: n.a. | B13: Magnetic | C13: Tokamak | D13: 1500 | E13: LCOE | F13: 10th-OAK | G13: Relative | H13: 39.4 | I13: EUR/MWh | J13: 2011 | K13: CF: 0.8 | L13: Optimistic scenario C; 40 years litetim; 2050-2060; 10 years construction time | M13: Bednyagin & Gnansounou (2011) | N13: Steady-State | O13: -
A14: n.a. | B14: Magnetic | C14: Tokamak | D14: 1500 | E14: LCOE | F14: Advanced NOAK | G14: Relative | H14: 36.4 | I14: EUR/MWh | J14: 2011 | K14: CF: 0.8 | L14: Optimistic scenario C; 40 years litetim; 2050-2060; 10 years construction time | M14: Bednyagin & Gnansounou (2011)
A15: n.a. | B15: Magnetic | C15: Tokamak | D15: 1500 | E15: LCOE | F15: Highly Advanced NOAK | G15: Relative | H15: 54.6 | I15: EUR/MWh | J15: 2011 | K15: CF: 0.8 | L15: Pessimistic scenario A; 40 years lifetime; 2060-2070; 10 years construction time | M15: Bednyagin & Gnansounou (2011) | N15: Steady-State | O15: -
A16: n.a. | B16: Magnetic | C16: Tokamak | D16: 1500 | E16: LCOE | F16: Highly Advanced NOAK | G16: Relative | H16: 42.9 | I16: EUR/MWh | J16: 2011 | K16: CF: 0.8 | L16: Scenario B; 40 years litetim; 2050-2060; 10 years construction time | M16: Bednyagin & Gnansounou (2011) | N16: Steady-State | O16: -
A17: n.a. | B17: Magnetic | C17: Tokamak | D17: 1500 | E17: LCOE | F17: Highly Advanced NOAK | G17: Relative | H17: 34.3 | I17: EUR/MWh | J17: 2011 | K17: CF: 0.8 | L17: Optimistic scenario C; 40 years litetim; 2050-2060; 10 years construction time | M17: Bednyagin & Gnansounou (2011) | N17: Steady-State | O17: -
A18: n.a. | B18: Magnetic | C18: Tokamak | D18: 1500 | E18: OCC | F18: FOAK | G18: Relative | H18: 8000 | I18: EUR/kW | J18: 2011 | K18: CF: 0.8 | L18: 40 years lifetime; 10 years construction time | M18: Bednyagin & Gnansounou (2011) | N18: Steady-State | O18: - | R18: Reactor | S18: Confinement type | T18: Reactor type | U18: Capacity [MW] | V18: Cost type | W18: Readiness | X18: Value | Y18: Unit | Z18: Cost base year | AA18: Comment | AB18: Reference
A19: MARS | B19: Magnetic | C19: Magnetic Mirror | D19: 1198 | E19: OCC | F19: 10th-OAK | G19: Absolute | H19: 4969000000 | I19: USD | J19: 1985 | K19: AV: 0.7 | L19: 6 years construction time | M19: Berwald et al. (1987) | N19: Steady-State | O19: 436000000 | R19: UWMAK-III | S19: Magnetic | T19: Tokamak | U19: 1985 | V19: OCC | W19: 10th-OAK | X19: 3270000000 | Y19: USD | Z19: 1975 | AB19: Badger et al. (1975)
A20: HYLIFE-I (single unit) | B20: Inertia | C20: Direct Drive | D20: 1010 | E20: OCC | F20: 10th-OAK | G20: Absolute | H20: 552000000 | I20: USD | J20: 1983 | K20: AV: 0.7 | L20: 30 years lifetime; 8 years construction time | M20: Blink et al. (1985) | N20: Steady State (due to high repetition rate of pulses) | O20: 328000000 | R20: n.a. | S20: Magnetic | T20: Tokamak | U20: 1500 | V20: OCC | W20: FOAK | X20: 8000 | Y20: EUR/kW | Z20: 2011 | AA20: 40 years lifetime; 10 years construction time | AB20: Bednyagin & Gnansounou (2011)
A21: n.a. | B21: Magnetic | C21: Tokamak | D21: 1500 | E21: LCOE | F21: NOAK | G21: Relative | H21: 54.8 | I21: EUR/MWh | J21: 2011 | L21: Scenario B; 40 years litetim; 2050-2060; 10 years construction time | M21: Bednyagin & Gnansounou (2011) | R21: MARS | S21: Magnetic | T21: Magnetic Mirror | U21: 1198 | V21: OCC | W21: 10th-OAK | X21: 4969000000 | Y21: USD | Z21: 1985 | AA21: 6 years construction time | AB21: Berwald et al. (1987)
A22: n.a. | B22: Magnetic | C22: Tokamak | D22: 1500 | E22: LCOE | F22: NOAK | G22: Relative | H22: 43.6 | I22: EUR/MWh | J22: 2011 | L22: Optimistic scenario C; 40 years litetim; 2050-2060; 10 years construction time | M22: Bednyagin & Gnansounou (2011) | R22: HYLIFE-I (single unit) | S22: Inertia | T22: Direct Drive | U22: 1010 | V22: OCC | W22: 10th-OAK | X22: 552000000 | Y22: USD | Z22: 1983 | AA22: 30 years lifetime; 8 years construction time | AB22: Blink et al. (1985)
A23: n.a. | B23: Magnetic | C23: Tokamak | D23: 1500 | E23: LCOE | F23: Advanced NOAK | G23: Relative | H23: 57.3 | I23: EUR/MWh | J23: 2011 | L23: Scenario B; 40 years litetim; 2050-2060; 10 years construction time | M23: Bednyagin & Gnansounou (2011) | R23: HYLIFE-I (dual unit) | S23: Inertia | T23: Direct Drive | U23: 2000 | V23: OCC | W23: 10th-OAK | X23: 855000000 | Y23: USD | Z23: 1983 | AA23: Dual-unit | AB23: Blink et al. (1985)
A24: n.a. | B24: Magnetic | C24: Tokamak | D24: 1500 | E24: LCOE | F24: Advanced NOAK | G24: Relative | H24: 45.6 | I24: EUR/MWh | J24: 2011 | L24: Optimistic scenario C; 40 years litetim; 2050-2060; 10 years construction time | M24: Bednyagin & Gnansounou (2011) | R24: STARFIRE | S24: Magnetic | T24: Tokamak | U24: 1200 | V24: OCC | W24: 10th-OAK | X24: 1.93553e+09 | Y24: USD | Z24: 1980 | AA24: 30 years lifetime; 6 years construction time | AB24: C.C. Baker et al. (1980)
A25: ARIES-I | B25: Magnetic | C25: Advanced Tokamak | D25: 1000 | E25: COE | F25: 10th-OAK | G25: Relative | H25: 100 | I25: mills/kWh | J25: 1992 | K25: - | M25: Najmabadi et al. (2006) | N25: - | O25: - | R25: V-Li/TOK (level safety assurance = 4) | S25: Magnetic | T25: Tokamak | U25: 1200 | V25: OCC | W25: 10th-OAK | X25: 2853000000 | Y25: USD | Z25: 1990 | AA25: Plant startup: 2025; 6 years construction time; 30 years lifetime | AB25: Delene (1991)
A26: ARIES-I (High-Field) | B26: Magnetic | C26: Advanced Tokamak | D26: 1000 | E26: COE | F26: 10th-OAK | G26: Relative | H26: 82 | I26: mills/kWh | J26: 1992 | K26: - | M26: Najmabadi et al. (2006) | N26: - | O26: - | R26: V-Li/TOK (level safety assurance = 3) | S26: Magnetic | T26: Tokamak | U26: 1200 | V26: OCC | W26: 10th-OAK | X26: 2547000000 | Y26: USD | Z26: 1990 | AA26: Plant startup: 2025; 6 years construction time; 30 years lifetime | AB26: Delene (1991)
A27: HYLIFE-I (dual unit) | B27: Inertia | C27: Direct Drive | D27: 2000 | E27: OCC | F27: 10th-OAK | G27: Absolute | H27: 855000000 | I27: USD | J27: 1983 | K27: AV: 0.7 | L27: Dual-unit | M27: Blink et al. (1985) | N27: Steady State (due to high repetition rate of pulses) | O27: 508000000 | R27: ARIES-I | S27: Magnetic | T27: Tokamak | U27: 1200 | V27: OCC | W27: 10th-OAK | X27: 4092000000 | Y27: USD | Z27: 1990 | AA27: Plant startup: 2025; 6 years construction time; 30 years lifetime | AB27: Delene (1991)
A28: STARFIRE | B28: Magnetic | C28: Tokamak | D28: 1200 | E28: OCC | F28: 10th-OAK | G28: Absolute | H28: 1.93553e+09 | I28: USD | J28: 1980 | K28: AV: 0.75 | L28: 30 years lifetime; 6 years construction time | M28: C.C. Baker et al. (1980) | N28: Steady-State with load-following ability: "Once operating, the reactor has the ability to load-follow at a rate of 5% of rated power increase or decrease per minute, although the reactor is designed as a base load unit" | O28: 188040000 | R28: Generomak - ESECOM - RAF-LiPb/RFP | S28: Magnetic | T28: Reversed-Field Pinch | U28: 1200 | V28: OCC | W28: 10th-OAK | X28: 1566300000 | Y28: USD | Z28: 1986 | AA28: 6 years construction time; 30 years lifetime | AB28: Delene et al. (1988)
A29: Modular Fusion Plant | B29: Magnetic | C29: Spherical Tokamak | D29: 735.77 | E29: COE | F29: FOAK | G29: Relative | H29: 0.06 | I29: USD/kWh | J29: 2009 | K29: CF. 0.95 | L29: Modular plant; learning effects due to mass prodction for modular parts | M29: Chuyanov et al. (2017) | N29: Steady-State | O29: - | R29: Generomak - ESECOM - V-Li/RFP | S29: Magnetic | T29: Reversed-Field Pinch | U29: 1200 | V29: OCC | W29: 10th-OAK | X29: 1589200000 | Y29: USD | Z29: 1986 | AA29: 6 years construction time; 30 years lifetime | AB29: Delene et al. (1988)
A30: CFETR (Full Superconducting Tokamak) | B30: Magnetic | C30: Tokamak | D30: 121.1 | E30: OCC | F30: FOAK | G30: Absolute | H30: 2579400000 | I30: USD | J30: 2009 | K30: Target: > 0.3-0.5 burning time | L30: Experimental; Without net electricity for output and needs external power supply | M30: Chen et al. (2015) | N30: Pulsed | O30: 434600000 | R30: ARIES-RS | S30: Magnetic | T30: Tokamak | U30: 1000 | V30: OCC | W30: 10th-OAK | X30: 3521500000 | Y30: USD | Z30: 1999 | AA30: 6 years construction time; 30 years lifetime | AB30: Delene et al. (2001)
A31: CFETR (Water-cooling Cu magnets) | B31: Magnetic | C31: Tokamak | D31: 121.1 | E31: OCC | F31: FOAK | G31: Absolute | H31: 1414500000 | I31: USD | J31: 2009 | K31: Target: > 0.3-0.5 burning time | L31: Experimental; Without net electricity for output and needs external power supply | M31: Chen et al. (2015) | N31: Pulsed | O31: 238300000 | R31: ARIES-ST | S31: Magnetic | T31: Tokamak | U31: 1000 | V31: OCC | W31: 10th-OAK | X31: 3880800000 | Y31: USD | Z31: 1999 | AA31: 6 years construction time; 30 years lifetime | AB31: Delene et al. (2001)
A32: V-Li/TOK (level safety assurance = 4) | B32: Magnetic | C32: Tokamak | D32: 1200 | E32: OCC | F32: 10th-OAK | G32: Absolute | H32: 2853000000 | I32: USD | J32: 1990 | K32: CF: 0.75 | L32: Plant startup: 2025; 6 years construction time; 30 years lifetime | M32: Delene (1991) | N32: Steady-State | O32: 557000000 | R32: Base Case Heliotron | S32: Magnetic | T32: Heliotron | U32: 1940 | V32: OCC | W32: NOAK | X32: 5767800000 | Y32: USD | Z32: 2003 | AB32: Dolan et al. (2005)
A33: V-Li/TOK (level safety assurance = 3) | B33: Magnetic | C33: Tokamak | D33: 1200 | E33: OCC | F33: 10th-OAK | G33: Absolute | H33: 2547000000 | I33: USD | J33: 1990 | K33: CF: 0.75 | L33: Plant startup: 2025; 6 years construction time; 30 years lifetime | M33: Delene (1991) | N33: Steady-State | O33: 469000000 | R33: New ARIES | S33: Magnetic | T33: Tokamak | U33: 1000 | V33: OCC | W33: 10th-OAK | X33: 2105150000 | Y33: USD | Z33: 1992 | AB33: Dragojlovic et al. (2010)
A34: ARIES-I | B34: Magnetic | C34: Tokamak | D34: 1200 | E34: OCC | F34: 10th-OAK | G34: Absolute | H34: 4092000000 | I34: USD | J34: 1990 | K34: CF: 0.75 | L34: Plant startup: 2025; 6 years construction time; 30 years lifetime | M34: Delene (1991) | N34: Steady-State | O34: 636000000 | R34: DEMO2 | S34: Magnetic | T34: Tokamak | U34: 953 | V34: OCC | W34: FOAK | X34: 7516000000 | Y34: USD | Z34: 2015 | AA34: 40 years lifetime; discount rate: 7%; 10 years construction time | AB34: Entler et al. (2018)
A35: STARFIRE | B35: Magnetic | C35: Tokamak | D35: 1200 | E35: Fuel Cost | F35: 10th-OAK | G35: Relative | H35: 0.04 | I35: mills/kWh | J35: 1980 | K35: - | M35: C.C. Baker et al. (1980) | N35: - | O35: - | R35: Fusion Power Corporation Reactor (incl. Hydrogen production) | S35: Inertia | T35: Ion Beam Driver | U35: 38000 | V35: OCC | W35: NOAK | X35: 75244000000 | Y35: USD | Z35: 2014 | AA35: Including hydrogen production | AB35: Helsley and Burke (2014)
A36: Generomak - ESECOM - V-LI/TOK | B36: Magnetic | C36: Tokamak | D36: 1200 | E36: Fuel Cost | F36: 10th-OAK | G36: Relative | H36: 0.35563751 | I36: USD/MWh | J36: 1986 | K36: - | M36: Delene et al. (1988) | N36: - | O36: - | R36: CREST | S36: Magnetic | T36: Tokamak | U36: 1160 | V36: OCC | W36: FOAK | X36: 7980000 | Y36: USD/MW | Z36: 2019 | AB36: Hiwatari and Goto (2019)
A37: Generomak - ESECOM - RAF-He/TOK | B37: Magnetic | C37: Tokamak | D37: 1200 | E37: Fuel Cost | F37: 10th-OAK | G37: Relative | H37: 0.35563751 | I37: USD/MWh | J37: 1986 | K37: - | M37: Delene et al. (1988) | N37: - | O37: - | R37: CREST | S37: Magnetic | T37: Tokamak | U37: 1160 | V37: OCC | W37: 10th-OAK | X37: 6870000 | Y37: USD/MW | Z37: 2019 | AB37: Hiwatari and Goto (2019)
A38: Generomak - ESECOM - RAF-LiPb/RFP | B38: Magnetic | C38: Reversed-Field Pinch | D38: 1200 | E38: Fuel Cost | F38: 10th-OAK | G38: Relative | H38: 0.35563751 | I38: USD/MWh | J38: 1986 | K38: - | M38: Delene et al. (1988) | N38: - | O38: - | R38: FPP_low | S38: Magneto-Inertial | T38: Stabilized Liner Compressor / Plasma Jet Driven Magneto-Inertial Fusion / Staged Z-Pinch / Sheared Flow Stabilized Z-Pinch | U38: 383.1 | V38: OCC | W38: Advanced NOAK | X38: 7.998e+08 | Y38: USD | Z38: 2020 | AA38: Four different fusion technologies: Stabilized Liner Compressor, Plansa Jet Driven Magneto-Intertial Fusion, Staged Z-Pinch, Sheared Flow Stabilized Z-Pinch; 6 years construction time | AB38: Hsu et al. (2020)
A39: Generomak - ESECOM - V-Li/RFP | B39: Magnetic | C39: Reversed-Field Pinch | D39: 1200 | E39: Fuel Cost | F39: 10th-OAK | G39: Relative | H39: 0.35563751 | I39: USD/MWh | J39: 1986 | K39: - | M39: Delene et al. (1988) | N39: - | O39: - | R39: FPP_high | S39: Magneto-Inertial | T39: Stabilized Liner Compressor / Plasma Jet Driven Magneto-Inertial Fusion / Staged Z-Pinch / Sheared Flow Stabilized Z-Pinch | U39: 814.4 | V39: OCC | W39: Advanced NOAK | X39: 1572000000 | Y39: USD | Z39: 2020 | AA39: Four different fusion technologies: Stabilized Liner Compressor, Plansa Jet Driven Magneto-Intertial Fusion, Staged Z-Pinch, Sheared Flow Stabilized Z-Pinch; 6 years construction time | AB39: Hsu et al. (2020)
A40: Generomak - ESECOM - SiC-He/TOK | B40: Magnetic | C40: Tokamak | D40: 1200 | E40: Fuel Cost | F40: 10th-OAK | G40: Relative | H40: 0.35563751 | I40: USD/MWh | J40: 1986 | K40: - | M40: Delene et al. (1988) | N40: - | O40: - | R40: Large Helical Device | S40: Magnetic | T40: Heliotron | U40: 1604 | V40: OCC | W40: NOAK | X40: 7270000000 | Y40: USD | Z40: 2002 | AA40: 40 years lifetime; discount rate: 3% | AB40: Kozaki et al. (2009)
A41: Generomak - ESECOM - V-FLiBe/TOK | B41: Magnetic | C41: Tokamak | D41: 1200 | E41: Fuel Cost | F41: 10th-OAK | G41: Relative | H41: 0.35563751 | I41: USD/MWh | J41: 1986 | K41: - | M41: Delene et al. (1988) | N41: - | O41: - | R41: Large Helical Device | S41: Magnetic | T41: Heliotron | U41: 1601 | V41: OCC | W41: NOAK | X41: 7393000000 | Y41: USD | Z41: 2002 | AA41: 40 years lifetime; discount rate: 3% | AB41: Kozaki et al. (2009)
A42: Generomak - ESECOM - V-MHD/TOK | B42: Magnetic | C42: Tokamak | D42: 1200 | E42: Fuel Cost | F42: 10th-OAK | G42: Relative | H42: 0.30821918 | I42: USD/MWh | J42: 1986 | K42: - | M42: Delene et al. (1988) | N42: - | O42: - | R42: Large Helical Device | S42: Magnetic | T42: Heliotron | U42: 1598 | V42: OCC | W42: NOAK | X42: 7705000000 | Y42: USD | Z42: 2002 | AA42: 40 years lifetime; discount rate: 3% | AB42: Kozaki et al. (2009)
A43: Generomak - ESECOM - V-DHe3/TOK | B43: Magnetic | C43: Tokamak | D43: 1200 | E43: Fuel Cost | F43: 10th-OAK | G43: Relative | H43: 2.0053272 | I43: USD/MWh | J43: 1986 | K43: - | L43: Fuel: D-He3 | M43: Delene et al. (1988) | N43: - | O43: - | R43: Large Helical Device | S43: Magnetic | T43: Heliotron | U43: 1598 | V43: OCC | W43: NOAK | X43: 6735000000 | Y43: USD | Z43: 2002 | AA43: 40 years lifetime; discount rate: 3% | AB43: Kozaki et al. (2009)
A44: New ARIES | B44: Magnetic | C44: Tokamak | D44: 1000 | E44: Fuel Cost | F44: 10th-OAK | G44: Relative | H44: 0.03 | I44: mills/kWh | J44: 1992 | K44: - | M44: Dragojlovic et al. (2010) | N44: - | O44: - | R44: ARIES-I | S44: Magnetic | T44: Tokamak | U44: 1000 | V44: OCC | W44: 10th-OAK | X44: 3289800000 | Y44: USD | Z44: 1992 | AA44: 40 years lifetime | AB44: Krakowski (1995)
A45: DEMO2 | B45: Magnetic | C45: Tokamak | D45: 953 | E45: Fuel Cost | F45: FOAK | G45: Relative | H45: 0.44 | I45: mills/kWh | J45: 2015 | K45: - | M45: Entler et al. (2018) | N45: - | O45: - | R45: ARIES-II | S45: Magnetic | T45: Tokamak | U45: 1000 | V45: OCC | W45: 10th-OAK | X45: 3060900000 | Y45: USD | Z45: 1992 | AA45: 40 years lifetime | AB45: Krakowski (1995)
A46: Option 1-Reactor - restructured | B46: Magnetic | C46: Stellarator | D46: 914 | E46: Fuel Cost | F46: FOAK | G46: Relative | H46: 0.20865035 | I46: USD/MWh | J46: 2023 | K46: - | M46: Famà et al. (2023) | N46: - | O46: - | R46: ARIES-III | S46: Magnetic | T46: Tokamak | U46: 1000 | V46: OCC | W46: 10th-OAK | X46: 3.1149e+09 | Y46: USD | Z46: 1992 | AA46: 40 years lifetime | AB46: Krakowski (1995)
A47: Option 2-Reactor - restructured | B47: Magnetic | C47: Stellarator | D47: 774 | E47: Fuel Cost | F47: FOAK | G47: Relative | H47: 0.24639072 | I47: USD/MWh | J47: 2023 | K47: - | M47: Famà et al. (2023) | N47: - | O47: - | R47: ARIES-IV | S47: Magnetic | T47: Tokamak | U47: 1000 | V47: OCC | W47: 10th-OAK | X47: 2746300000 | Y47: USD | Z47: 1992 | AA47: 40 years lifetime | AB47: Krakowski (1995)
A48: Option 3-Reactor - restructured | B48: Magnetic | C48: Stellarator | D48: 1945 | E48: Fuel Cost | F48: FOAK | G48: Relative | H48: 0.098049573 | I48: USD/MWh | J48: 2023 | K48: - | M48: Famà et al. (2023) | N48: - | O48: - | R48: Commercial breeder | S48: Magnetic | T48: Tandem Mirror | U48: 1100 | V48: OCC | W48: 10th-OAK | X48: 3637000000 | Y48: USD | Z48: 1982 | AA48: Selling excess electricity and fissile material to commercial markets while producing tritium and plutonium | AB48: Lee (1987)
A49: Option 4-Reactor - restructured | B49: Magnetic | C49: Stellarator | D49: 1165 | E49: Fuel Cost | F49: FOAK | G49: Relative | H49: 0.1636965 | I49: USD/MWh | J49: 2023 | K49: - | M49: Famà et al. (2023) | N49: - | O49: - | R49: Early large | S49: Magnetic | T49: Tokamak | U49: 1500 | V49: OCC | W49: NOAK | X49: 11580 | Y49: USD/kW | Z49: 2020 | AB49: Lindley et al. (2023)
A50: Option 1-Reactor - Greenfield | B50: Magnetic | C50: Stellarator | D50: 1204 | E50: Fuel Cost | F50: FOAK | G50: Relative | H50: 0.15839404 | I50: USD/MWh | J50: 2023 | K50: - | M50: Famà et al. (2023) | N50: - | O50: - | R50: Early large | S50: Magnetic | T50: Tokamak | U50: 1500 | V50: OCC | W50: 10th-OAK | X50: 8168 | Y50: USD/kW | Z50: 2020 | AB50: Lindley et al. (2023)
A51: Option 2-Reactor - Greenfield | B51: Magnetic | C51: Stellarator | D51: 1313 | E51: Fuel Cost | F51: FOAK | G51: Relative | H51: 0.1452448 | I51: USD/MWh | J51: 2023 | K51: - | M51: Famà et al. (2023) | N51: - | O51: - | R51: Advanced Large | S51: Magnetic | T51: Tokamak | U51: 1500 | V51: OCC | W51: NOAK | X51: 7733 | Y51: USD/kW | Z51: 2020 | AB51: Lindley et al. (2023)
A52: Option 3-Reactor - Greenfield | B52: Magnetic | C52: Stellarator | D52: 2272 | E52: Fuel Cost | F52: FOAK | G52: Relative | H52: 0.083937685 | I52: USD/MWh | J52: 2023 | K52: - | M52: Famà et al. (2023) | N52: - | O52: - | R52: Advanced Large | S52: Magnetic | T52: Tokamak | U52: 1500 | V52: OCC | W52: 10th-OAK | X52: 5747 | Y52: USD/kW | Z52: 2020 | AB52: Lindley et al. (2023)
A53: Option 4-Reactor - Greenfield | B53: Magnetic | C53: Stellarator | D53: 1368 | E53: Fuel Cost | F53: FOAK | G53: Relative | H53: 0.13940528 | I53: USD/MWh | J53: 2023 | K53: - | M53: Famà et al. (2023) | N53: - | O53: - | R53: CFETR (Full Superconducting Tokamak) | S53: Magnetic | T53: Tokamak | U53: 121.1 | V53: OCC | W53: FOAK | X53: 2579400000 | Y53: USD | Z53: 2009 | AA53: Experimental; Without net electricity for output and needs external power supply | AB53: Chen et al. (2015)
A54: Conventional R&D | B54: Magnetic | C54: Tokamak | D54: 1000 | E54: Fuel Cost | F54: 10th-OAK | G54: Relative | H54: 2 | I54: USD/MWh | J54: 2000 | K54: - | L54: Fuel and back-end costs | M54: Gi et al. (2020) | N54: - | O54: - | R54: CFETR (Water-cooling Cu magnets) | S54: Magnetic | T54: Tokamak | U54: 121.1 | V54: OCC | W54: FOAK | X54: 1414500000 | Y54: USD | Z54: 2009 | AA54: Experimental; Without net electricity for output and needs external power supply | AB54: Chen et al. (2015)
A55: Advanced R&D | B55: Magnetic | C55: Tokamak | D55: 1000 | E55: Fuel Cost | F55: 10th-OAK | G55: Relative | H55: 2 | I55: USD/MWh | J55: 2000 | K55: - | L55: Fuel and back-end costs | M55: Gi et al. (2020) | N55: - | O55: - | R55: CASCADE (all Conventional) | S55: Inertia | T55: Direct Drive | U55: 815 | V55: OCC | W55: 10th-OAK | X55: 1233000000 | Y55: USD | Z55: 1985 | AA55: 6 years construction time; 30 years lifetime | AB55: Maya et al. (1985)
A56: FPP_low | B56: Magneto-Inertial | C56: SLC / PJMIF / Staged Z-Pinch / SFS Z-Pinch | D56: 383.1 | E56: Fuel Cost | F56: Advanced NOAK | G56: Relative | H56: 0.033108632 | I56: USD/MWh | J56: 2020 | K56: - | M56: Hsu et al. (2020) | N56: - | O56: - | R56: CASCADE | S56: Inertia | T56: Direct Drive | U56: 815 | V56: OCC | W56: 10th-OAK | X56: 1559800000 | Y56: USD | Z56: 1985 | AA56: 6 years construction time; 30 years lifetime | AB56: Maya et al. (1985)
A57: FPP_high | B57: Magneto-Inertial | C57: SLC / PJMIF / Staged Z-Pinch / SFS Z-Pinch | D57: 814.4 | E57: Fuel Cost | F57: Advanced NOAK | G57: Relative | H57: 0.015574554 | I57: USD/MWh | J57: 2020 | K57: - | M57: Hsu et al. (2020) | N57: - | O57: - | R57: Reactor based on SCAN Code | S57: Magnetic | T57: Tokamak | U57: 1200 | V57: OCC | W57: FOAK | X57: 7227000000 | Y57: USD | Z57: 1990 | AB57: Miller et al. (1991)
A58: Large Helical Device | B58: Magnetic | C58: Heliotron | D58: 1604 | E58: Fuel Cost | F58: NOAK | G58: Relative | H58: 0.023 | I58: mills/kWh | J58: 2002 | K58: - | M58: Kozaki et al. (2009) | N58: - | O58: - | R58: Reactor based on ARIES Code | S58: Magnetic | T58: Tokamak | U58: 1200 | V58: OCC | W58: 10th-OAK | X58: 3646000000 | Y58: USD | Z58: 1990 | AA58: 6 years construction time; 30 years lifetime | AB58: Miller et al. (1991)
A59: Large Helical Device | B59: Magnetic | C59: Heliotron | D59: 1601 | E59: Fuel Cost | F59: NOAK | G59: Relative | H59: 0.022 | I59: mills/kWh | J59: 2002 | K59: - | M59: Kozaki et al. (2009) | N59: - | O59: - | R59: ARIES-I | S59: Magnetic | T59: Tokamak | U59: 1000 | V59: OCC | W59: 10th-OAK | X59: 2.89e+09 | Y59: USD | Z59: 1988 | AB59: Najmabadi et al. (1991)
A60: Large Helical Device | B60: Magnetic | C60: Heliotron | D60: 1598 | E60: Fuel Cost | F60: NOAK | G60: Relative | H60: 0.021 | I60: mills/kWh | J60: 2002 | K60: - | M60: Kozaki et al. (2009) | N60: - | O60: - | R60: ARIES-AT | S60: Magnetic | T60: Tokamak | U60: 1000 | V60: OCC | W60: 10th-OAK | X60: 2129000000 | Y60: USD | Z60: 1992 | AA60: 40 years lifetime | AB60: Najmabadi et al. (2006)
A61: Large Helical Device | B61: Magnetic | C61: Heliotron | D61: 1598 | E61: Fuel Cost | F61: NOAK | G61: Relative | H61: 0.021 | I61: mills/kWh | J61: 2002 | K61: - | M61: Kozaki et al. (2009) | N61: - | O61: - | R61: SSTR-like DEMO | S61: Magnetic | T61: Tokamak | U61: 1080 | V61: OCC | W61: FOAK | X61: 4228700000 | Y61: USD | Z61: 2003 | AA61: 30 years lifetime | AB61: Oishi et al. (2012)
A62: ARIES-III | B62: Magnetic | C62: Tokamak | D62: 1000 | E62: Fuel Cost | F62: 10th-OAK | G62: Relative | H62: 17.5 | I62: mills/kWh | J62: 1992 | K62: - | L62: Lunar; D-He3 | M62: Krakowski (1995) | N62: - | O62: - | R62: European Model C Reactor | S62: Magnetic | T62: Tokamak | U62: 1450 | V62: OCC | W62: 10th-OAK | X62: 6093.0435 | Y62: USD/kW | Z62: 2010 | AA62: 6 years construction time; 40 years lifetime | AB62: Sheffield and Milora (2016)
A63: ARIES-II | B63: Magnetic | C63: Tokamak | D63: 1000 | E63: Fuel Cost | F63: 10th-OAK | G63: Relative | H63: 0.03 | I63: mills/kWh | J63: 1992 | K63: - | M63: Krakowski (1995) | N63: - | O63: - | R63: ARIES-AT | S63: Magnetic | T63: Tokamak | U63: 1000 | V63: OCC | W63: 10th-OAK | X63: 2849 | Y63: USD/kW | Z63: 2000 | AB63: Han and Ward (2009)
A64: ARIES-IV | B64: Magnetic | C64: Tokamak | D64: 1000 | E64: Fuel Cost | F64: 10th-OAK | G64: Relative | H64: 0.03 | I64: mills/kWh | J64: 1992 | K64: - | M64: Krakowski (1995) | N64: - | O64: - | R64: Fusion basic early | S64: Magnetic | T64: Tokamak | U64: 1000 | V64: OCC | W64: 10th-OAK | X64: 3940 | Y64: USD/kW | Z64: 2000 | AA64: in 2050 | AB64: Han and Ward (2009)
A65: ARIES-I | B65: Magnetic | C65: Tokamak | D65: 1000 | E65: Fuel Cost | F65: 10th-OAK | G65: Relative | H65: 0.03 | I65: mills/kWh | J65: 1992 | K65: - | M65: Krakowski (1995) | N65: - | O65: - | R65: Fusion basic early mature | S65: Magnetic | T65: Tokamak | U65: 1000 | V65: OCC | W65: Highly Advanced NOAK | X65: 2950 | Y65: USD/kW | Z65: 2000 | AA65: in 2060 | AB65: Han and Ward (2009)
A66: Reactor based on ARIES Code | B66: Magnetic | C66: Tokamak | D66: 1200 | E66: Fuel Cost | F66: 10th-OAK | G66: Relative | H66: 0.06 | I66: mills/kWh | J66: 1990 | K66: - | M66: Miller et al. (1991) | N66: - | O66: - | R66: Fusion Advanced early | S66: Magnetic | T66: Tokamak | U66: 1000 | V66: OCC | W66: 10th-OAK | X66: 2820 | Y66: USD/kW | Z66: 2000 | AA66: in 2070 | AB66: Han and Ward (2009)
A67: Reactor based on SCAN Code | B67: Magnetic | C67: Tokamak | D67: 1200 | E67: Fuel Cost | F67: FOAK | G67: Relative | H67: 0.05 | I67: mills/kWh | J67: 1990 | K67: - | M67: Miller et al. (1991) | N67: - | O67: - | R67: Fusion Advanced mature | S67: Magnetic | T67: Tokamak | U67: 1000 | V67: OCC | W67: Highly Advanced NOAK | X67: 2170 | Y67: USD/kW | Z67: 2000 | AA67: in 2080 | AB67: Han and Ward (2009)
A68: HYLIFE-II | B68: Inertia | C68: Ion Beam Driver | D68: 1083 | E68: Fuel Cost | F68: 10th-OAK | G68: Relative | H68: 0.01 | I68: mills/kWh | J68: 1988 | K68: - | M68: Moir (1992) | N68: - | O68: - | R68: PPCS-A | S68: Magnetic | T68: Tokamak | U68: 1000 | V68: OCC | W68: 10th-OAK | X68: 5625 | Y68: USD/kW | Z68: 2000 | AB68: Han and Ward (2009)
A69: ARIES-I | B69: Magnetic | C69: Tokamak | D69: 1000 | E69: Fuel Cost | F69: 10th-OAK | G69: Relative | H69: 0.04 | I69: mills/kWh | J69: 1988 | K69: - | M69: Najmabadi et al. (1991) | N69: - | O69: - | R69: PPCS-B | S69: Magnetic | T69: Tokamak | U69: 1000 | V69: OCC | W69: 10th-OAK | X69: 5215 | Y69: USD/kW | Z69: 2000 | AB69: Han and Ward (2009)
A70: ARIES-AT | B70: Magnetic | C70: Tokamak | D70: 1000 | E70: Fuel Cost | F70: 10th-OAK | G70: Relative | H70: 0.03 | I70: mills/kWh | J70: 1992 | K70: - | M70: Najmabadi et al. (2006) | N70: - | O70: - | R70: PPCS-C | S70: Magnetic | T70: Tokamak | U70: 1000 | V70: OCC | W70: 10th-OAK | X70: 4155 | Y70: USD/kW | Z70: 2000 | AB70: Han and Ward (2009)
A71: Generic Toroidal Reactor | B71: Magnetic | C71: Tokamak | D71: 1000 | E71: Fuel Cost | F71: 10th-OAK | G71: Relative | H71: 0.057077626 | I71: USD/MWh | J71: 2010 | M71: Sheffield and Milora (2016) | R71: PPCS-D | S71: Magnetic | T71: Tokamak | U71: 1000 | V71: OCC | W71: 10th-OAK | X71: 2868 | Y71: USD/kW | Z71: 2000 | AB71: Han and Ward (2009)
A72: Generomak - ESECOM - RAF-LiPb/RFP | B72: Magnetic | C72: Reversed-Field Pinch | D72: 1200 | E72: OCC | F72: 10th-OAK | G72: Absolute | H72: 1566300000 | I72: USD | J72: 1986 | K72: CF: 0.65 | L72: 6 years construction time; 30 years lifetime | M72: Delene et al. (1988) | N72: Steady-State | O72: 234900000 | R72: Generic Toroidal Reactor | S72: Magnetic | T72: Tokamak | U72: 1000 | V72: OCC | W72: 10th-OAK | X72: 6252.0652 | Y72: USD/kW | Z72: 2010 | AA72: 6 years construction time; 30 years lifetime | AB72: Sheffield and Milora (2016)
A73: Generomak - ESECOM - V-Li/RFP | B73: Magnetic | C73: Reversed-Field Pinch | D73: 1200 | E73: OCC | F73: 10th-OAK | G73: Absolute | H73: 1589200000 | I73: USD | J73: 1986 | K73: CF: 0.65 | L73: 6 years construction time; 30 years lifetime | M73: Delene et al. (1988) | N73: Steady-State | O73: 238400000 | R73: ARIES-RS | S73: Magnetic | T73: Tokamak | U73: 1000 | V73: OCC | W73: 10th-OAK | X73: 4897.2522 | Y73: USD/kW | Z73: 2010 | AA73: 7 years Construction time | AB73: Sheffield and Milora (2016)
A74: Generomak - ESECOM - V-LI/TOK | B74: Magnetic | C74: Tokamak | D74: 1200 | E74: OCC | F74: 10th-OAK | G74: Absolute | H74: 2273100000 | I74: USD | J74: 1986 | K74: CF: 0.65 | L74: 6 years construction time; 30 years lifetime | M74: Delene et al. (1988) | N74: Steady-State | O74: 341000000 | R74: ARIES-AT | S74: Magnetic | T74: Tokamak | U74: 1000 | V74: OCC | W74: 10th-OAK | X74: 3045.3261 | Y74: USD/kW | Z74: 2010 | AA74: 6 years Construction time | AB74: Sheffield and Milora (2016)
A75: European Model C Reactor | B75: Magnetic | C75: Tokamak | D75: 1450 | E75: Fuel Cost | F75: 10th-OAK | G75: Relative | H75: 0.041988138 | I75: USD/MWh | J75: 2010 | M75: Sheffield and Milora (2016) | R75: SSTR | S75: Magnetic | T75: Tokamak | U75: 1000 | V75: OCC | W75: FOAK | X75: 6326914000 | Y75: USD | Z75: 1996 | AB75: Kikuchi et al. (1996)
A76: ARIES-RS | B76: Magnetic | C76: Tokamak | D76: 1000 | E76: Fuel Cost | F76: 10th-OAK | G76: Relative | H76: 0.053720118 | I76: USD/MWh | J76: 2010 | K76: AV: 0.85 | M76: Sheffield and Milora (2016) | R76: A-SSTR | S76: Magnetic | T76: Tokamak | U76: 1700 | V76: OCC | W76: NOAK | X76: 4697100000 | Y76: USD | Z76: 1996 | AA76: 4 years construction time | AB76: Kikuchi et al. (1996)
A77: Generomak - ESECOM - RAF-He/TOK | B77: Magnetic | C77: Tokamak | D77: 1200 | E77: OCC | F77: 10th-OAK | G77: Absolute | H77: 2288500000 | I77: USD | J77: 1986 | K77: CF: 0.65 | L77: 6 years construction time; 30 years lifetime | M77: Delene et al. (1988) | N77: Steady-State | O77: 343000000 | R77: ARIES-AT Advanced | S77: Magnetic | T77: Tokamak | U77: 1000 | V77: OCC | W77: 10th-OAK | X77: 3949.2391 | Y77: USD/kW | Z77: 2010 | AA77: 6 years Construction time | AB77: Sheffield and Milora (2016)
A78: Generomak - ESECOM - SiC-He/TOK | B78: Magnetic | C78: Tokamak | D78: 1200 | E78: OCC | F78: 10th-OAK | G78: Absolute | H78: 2675000000 | I78: USD | J78: 1986 | K78: CF: 0.65 | L78: 6 years construction time; 30 years lifetime | M78: Delene et al. (1988) | N78: Steady-State | O78: 401200000 | R78: STARFIRE | S78: Magnetic | T78: Tokamak | U78: 1200 | V78: OCC | W78: 10th-OAK | X78: 2307000000 | Y78: USD | Z78: 1983 | AA78: 30 years lifetime | AB78: Sheffield et al. (1986)
A79: ARIES-AT | B79: Magnetic | C79: Tokamak | D79: 1000 | E79: Fuel Cost | F79: 10th-OAK | G79: Relative | H79: 0.053720118 | I79: USD/MWh | J79: 2010 | K79: AV: 0.85 | M79: Sheffield and Milora (2016) | R79: PCSR-E | S79: Magnetic | T79: Tokamak | U79: 1247 | V79: OCC | W79: FOAK | X79: 6121062000 | Y79: USD | Z79: 1984 | AA79: 8 years construction time ; 25 years lifetime; converted from ECU to USD | AB79: Spears in Safety, Environmental Impact, and Economic Prospects of Nuclear Fusion (1990)
A80: ARIES-AT Advanced | B80: Magnetic | C80: Tokamak | D80: 1000 | E80: Fuel Cost | F80: 10th-OAK | G80: Relative | H80: 0.053720118 | I80: USD/MWh | J80: 2010 | K80: AV: 0.85 | M80: Sheffield and Milora (2016) | R80: Reactor-1 | S80: Magnetic | T80: Tokamak | U80: 1203 | V80: OCC | W80: FOAK | X80: 5801517000 | Y80: USD | Z80: 1984 | AA80: 8 years construction time ; 25 years lifetime | AB80: Spears in Safety, Environmental Impact, and Economic Prospects of Nuclear Fusion (1990)
A81: STARFIRE | B81: Magnetic | C81: Tokamak | D81: 1200 | E81: Fuel Cost | F81: 10th-OAK | G81: Relative | H81: 0.058541154 | I81: USD/MWh | J81: 1983 | K81: - | M81: Sheffield et al. (1986) | N81: - | O81: - | R81: Reactor-2 | S81: Magnetic | T81: Tokamak | U81: 1209 | V81: OCC | W81: FOAK | X81: 4251921000 | Y81: USD | Z81: 1984 | AA81: 8 years construction time ; 25 years lifetime | AB81: Spears in Safety, Environmental Impact, and Economic Prospects of Nuclear Fusion (1990)
A82: Prometheus-L | B82: Inertia | C82: Direct Drive | D82: 972 | E82: Fuel Cost | F82: 10th-OAK | G82: Relative | H82: 0.6034889 | I82: USD/MWh | J82: 1991 | K82: AV: 0.794 | M82: Waganer et al. (1992) | N82: Steady-State (possible due to high repetition rate of laser pulses (nearly 15 per second)) | O82: - | R82: Commercial Twin Reactor | S82: Magnetic | T82: Tokamak | U82: 1500 | V82: OCC | W82: Advanced NOAK | X82: 2576 | Y82: EUR/kW | Z82: 1998 | AA82: in 2100; 6.25 years construction time | AB82: Lako & Seebregts (1998)
A83: Prometheus-H | B83: Inertia | C83: Indirect Drive | D83: 999 | E83: Fuel Cost | F83: 10th-OAK | G83: Relative | H83: 0.8283181 | I83: USD/MWh | J83: 1991 | K83: AV: 0.808 | M83: Waganer et al. (1992) | N83: Steady-State (possible due to high repetition rate of laser pulses (nearly 15 per second)) | O83: - | R83: Commercial Twin Reactor | S83: Magnetic | T83: Tokamak | U83: 1500 | V83: OCC | W83: 10th-OAK | X83: 2926 | Y83: EUR/kW | Z83: 1998 | AA83: in 2070; 6.25 years construction time | AB83: Lako & Seebregts (1998)
A84: Tokamak Reactor-1 | B84: Magnetic | C84: Tokamak | D84: 1000 | E84: Fuel Cost | F84: NOAK | G84: Relative | H84: 0.04 | I84: mills/kWh | J84: 2003 | K84: - | L84: 30 years lifetime | M84: Yamazaki et al. (2009) | N84: - | O84: - | R84: Commercial Single Reactor | S84: Magnetic | T84: Tokamak | U84: 1000 | V84: OCC | W84: NOAK | X84: 5220 | Y84: EUR/kW | Z84: 1998 | AA84: in 2050; 6.25 years construction time | AB84: Lako & Seebregts (1998)
A85: Spherical Reactor-1 | B85: Magnetic | C85: Spherical Tokamak | D85: 1000 | E85: Fuel Cost | F85: NOAK | G85: Relative | H85: 0.04 | I85: mills/kWh | J85: 2003 | K85: - | L85: 30 years lifetime | M85: Yamazaki et al. (2009) | N85: - | O85: - | R85: DEMO | S85: Magnetic | T85: Tokamak | U85: 1000 | V85: OCC | W85: FOAK | X85: 7906 | Y85: EUR/kW | Z85: 1998 | AA85: in 2020; 7 years construction time; ITER-type | AB85: Lako & Seebregts (1998)
A86: Helical Reactor-1 | B86: Magnetic | C86: Heliotron | D86: 1000 | E86: Fuel Cost | F86: NOAK | G86: Relative | H86: 0.04 | I86: mills/kWh | J86: 2003 | K86: - | L86: 30 years lifetime | M86: Yamazaki et al. (2009) | N86: - | O86: - | R86: UWMAK-III | S86: Magnetic | T86: Tokamak | U86: 1185 | V86: OCC | W86: 10th-OAK | X86: 3609000000 | Y86: USD | Z86: 1976 | AA86: 30 years lifetime | AB86: Tsoulfanidis (1981)
A87: Generomak - ESECOM - V-FLiBe/TOK | B87: Magnetic | C87: Tokamak | D87: 1200 | E87: OCC | F87: 10th-OAK | G87: Absolute | H87: 1953700000 | I87: USD | J87: 1986 | K87: CF: 0.65 | L87: 6 years construction time; 30 years lifetime | M87: Delene et al. (1988) | N87: Steady-State | O87: 293000000 | R87: Prometheus-L | S87: Inertia | T87: Direct Drive | U87: 972 | V87: OCC | W87: 10th-OAK | X87: 3929900000 | Y87: USD | Z87: 1991 | AA87: Construction time: 6 years | AB87: Waganer et al. (1992)
A88: ARIES-RS_max | B88: Magnetic | C88: Tokamak | D88: 1000 | E88: LCOE | F88: 10th-OAK | G88: Relative | H88: 103 | I88: mills/kWh | J88: 1999 | K88: CF: 0.7 | M88: Delene et al. (2001) | N88: Steady-State | O88: - | R88: Small | S88: Magnetic | T88: Tokamak | U88: 200 | V88: OCC | W88: NOAK | X88: 16343 | Y88: USD/kW | Z88: 2020 | AA88: 4-5 years construction time | AB88: Lindley et al. (2023)
A89: ARIES-ST_max | B89: Magnetic | C89: Tokamak | D89: 1000 | E89: LCOE | F89: 10th-OAK | G89: Relative | H89: 110 | I89: mills/kWh | J89: 1999 | K89: CF: 0.7 | M89: Delene et al. (2001) | N89: Steady-State | O89: - | R89: Small | S89: Magnetic | T89: Tokamak | U89: 200 | V89: OCC | W89: 10th-OAK | X89: 12095 | Y89: USD/kW | Z89: 2020 | AA89: 4-5 years construction time | AB89: Lindley et al. (2023)
A90: ARIES-RS | B90: Magnetic | C90: Tokamak | D90: 1300 | E90: LCOE | F90: 10th-OAK | G90: Relative | H90: 80 | I90: mills/kWh | J90: 1999 | K90: CF: 0.8 | M90: Delene et al. (2001) | N90: Steady-State | O90: - | R90: Small | S90: Magnetic | T90: Tokamak | U90: 200 | V90: OCC | W90: Advanced NOAK | X90: 7219 | Y90: USD/kW | Z90: 2020 | AA90: 4-5 years construction time | AB90: Lindley et al. (2023)
A91: ARIES-RS | B91: Magnetic | C91: Tokamak | D91: 1000 | E91: LCOE | F91: 10th-OAK | G91: Relative | H91: 90 | I91: mills/kWh | J91: 1999 | K91: CF: 0.8 | M91: Delene et al. (2001) | N91: Steady-State | O91: - | R91: Generomak - ESECOM - V-Li/TOK | S91: Magnetic | T91: Tokamak | U91: 1200 | V91: OCC | W91: 10th-OAK | X91: 2178 | Y91: USD/kW | Z91: 1986 | AA91: Based on ESECOM study and GENEROMAK reactor; 6 years construction time; 30 years lifetime | AB91: Logan et al. in Safety, Environmental Impact, and Economic Prospects of Nuclear Fusion (1990)
A92: ARIES-ST | B92: Magnetic | C92: Tokamak | D92: 1300 | E92: LCOE | F92: 10th-OAK | G92: Relative | H92: 86 | I92: mills/kWh | J92: 1999 | K92: CF: 0.8 | M92: Delene et al. (2001) | N92: Steady-State | O92: - | R92: Generomak - ESECOM - RAF-He/TOK | S92: Magnetic | T92: Tokamak | U92: 1200 | V92: OCC | W92: 10th-OAK | X92: 2193 | Y92: USD/kW | Z92: 1986 | AA92: Based on ESECOM study and GENEROMAK reactor; 6 years construction time; 30 years lifetime | AB92: Logan et al. in Safety, Environmental Impact, and Economic Prospects of Nuclear Fusion (1990)
A93: ARIES-ST | B93: Magnetic | C93: Tokamak | D93: 1000 | E93: LCOE | F93: 10th-OAK | G93: Relative | H93: 95 | I93: mills/kWh | J93: 1999 | K93: CF: 0.8 | M93: Delene et al. (2001) | N93: Steady-State | O93: - | R93: Generomak - ESECOM - RAF-LiPb/RFP | S93: Magnetic | T93: Reversed-Field Pinch | U93: 970 | V93: OCC | W93: 10th-OAK | X93: 1501 | Y93: USD/kW | Z93: 1986 | AA93: Based on ESECOM study and GENEROMAK reactor; 6 years construction time; 30 years lifetime | AB93: Logan et al. in Safety, Environmental Impact, and Economic Prospects of Nuclear Fusion (1990)
A94: Generomak - ESECOM - V-MHD/TOK | B94: Magnetic | C94: Tokamak | D94: 1200 | E94: OCC | F94: 10th-OAK | G94: Absolute | H94: 1439800000 | I94: USD | J94: 1986 | K94: CF: 0.75 | L94: 6 years construction time; 30 years lifetime | M94: Delene et al. (1988) | N94: Steady-State | O94: 216000000 | R94: Generomak - ESECOM - V-Li/RFP | S94: Magnetic | T94: Reversed-Field Pinch | U94: 970 | V94: OCC | W94: 10th-OAK | X94: 1523 | Y94: USD/kW | Z94: 1986 | AA94: Based on ESECOM study and GENEROMAK reactor; 6 years construction time; 30 years lifetime | AB94: Logan et al. in Safety, Environmental Impact, and Economic Prospects of Nuclear Fusion (1990)
A95: Generomak - ESECOM - V-DHe3/TOK | B95: Magnetic | C95: Tokamak | D95: 1200 | E95: OCC | F95: 10th-OAK | G95: Absolute | H95: 2907700000 | I95: USD | J95: 1986 | K95: CF: 0.75 | L95: 6 years construction time; 30 years lifetime | M95: Delene et al. (1988) | N95: Steady-State | O95: 436200000 | R95: Generomak - ESECOM - SiC-He/TOK | S95: Magnetic | T95: Tokamak | U95: 1200 | V95: OCC | W95: 10th-OAK | X95: 2563 | Y95: USD/kW | Z95: 1986 | AA95: Based on ESECOM study and GENEROMAK reactor; 6 years construction time; 30 years lifetime | AB95: Logan et al. in Safety, Environmental Impact, and Economic Prospects of Nuclear Fusion (1990)
A96: ARIES-ST_min | B96: Magnetic | C96: Tokamak | D96: 1300 | E96: LCOE | F96: 10th-OAK | G96: Relative | H96: 68 | I96: mills/kWh | J96: 1999 | K96: CF: 0.9 | M96: Delene et al. (2001) | N96: Steady-State | O96: - | R96: Generomak - ESECOM - V-FLiBe/TOK | S96: Magnetic | T96: Tokamak | U96: 1200 | V96: OCC | W96: 10th-OAK | X96: 1873 | Y96: USD/kW | Z96: 1986 | AA96: Based on ESECOM study and GENEROMAK reactor; 6 years construction time; 30 years lifetime | AB96: Logan et al. in Safety, Environmental Impact, and Economic Prospects of Nuclear Fusion (1990)
A97: ARIES-RS_min | B97: Magnetic | C97: Tokamak | D97: 1300 | E97: LCOE | F97: 10th-OAK | G97: Relative | H97: 65 | I97: mills/kWh | J97: 1999 | K97: CF: 0.9 | M97: Delene et al. (2001) | N97: Steady-State | O97: - | R97: Generomak - ESECOM - V-MHD/TOK | S97: Magnetic | T97: Tokamak | U97: 1200 | V97: OCC | W97: 10th-OAK | X97: 1380 | Y97: USD/kW | Z97: 1986 | AA97: Based on ESECOM study and GENEROMAK reactor; 6 years construction time; 30 years lifetime | AB97: Logan et al. in Safety, Environmental Impact, and Economic Prospects of Nuclear Fusion (1990)
A98: NLHD-D1 Scaling Heliotron | B98: Magnetic | C98: Heliotron | D98: 1000 | E98: LCOE | F98: NOAK | G98: Relative | H98: 93 | I98: mills/kWh | J98: 2003 | K98: AV: 0.75 | L98: 6 years construction time | M98: Dolan et al. (2005) | N98: Steady-State | O98: - | R98: Generomak - ESECOM - V-D3He/TOK | S98: Magnetic | T98: Tokamak | U98: 1200 | V98: OCC | W98: 10th-OAK | X98: 2787 | Y98: USD/kW | Z98: 1986 | AA98: Based on ESECOM study and GENEROMAK reactor; 6 years construction time; 30 years lifetime | AB98: Logan et al. in Safety, Environmental Impact, and Economic Prospects of Nuclear Fusion (1990)
A99: ARIES-SPSS | B99: Magnetic | C99: Stellarator | D99: 1000 | E99: LCOE | F99: 10th-OAK | G99: Relative | H99: 91 | I99: mills/kWh | J99: 2003 | K99: AV: 0.75 | L99: Modular; 6 years construction time | M99: Dolan et al. (2005) | N99: Steady-State | O99: - | R99: Prometheus-H | S99: Inertia | T99: Indirect Drive | U99: 999 | V99: OCC | W99: 10th-OAK | X99: 2716020000 | Y99: USD | Z99: 1991 | AA99: Construction time: 6 years | AB99: Waganer et al. (1992)
A100: New ARIES | B100: Magnetic | C100: Tokamak | D100: 1000 | E100: COE | F100: 10th-OAK | G100: Relative | H100: 47.12 | I100: mills/kWh | J100: 1992 | K100: CF: 0.85 | L100: 6 years construction time | M100: Dragojlovic et al. (2010) | N100: Steady-State | O100: - | R100: HYLIFE-II | S100: Inertia | T100: Ion Beam Driver | U100: 1083 | V100: OCC | W100: 10th-OAK | X100: 4231500000 | Y100: USD | Z100: 1988 | AA100: 30 years lifetime | AB100: Moir (1992)
A101: Option 1-Reactor - Greenfield | B101: Magnetic | C101: Stellarator | D101: 1204 | E101: LCOE | F101: FOAK | G101: Relative | H101: 87 | I101: USD/MWh | J101: 2023 | K101: CF: 0.85 | L101: Greenfield reference plant where everything has been built from zero/without restructuring | M101: Famà et al. (2023) | N101: Steady-State | O101: - | R101: ITER-like | S101: Magnetic | T101: Tokamak | U101: 1000 | V101: OCC | W101: FOAK | X101: 5324.3478 | Y101: USD/kW | Z101: 2010 | AA101: 10 years Construction time | AB101: Sheffield and Milora (2016)
...

Sheet Cost data collection_clean
A2: As found in literature | W2: Prometheus: https://aries.pppl.gov/LIB/REPORT/OTHER/PROMETHEUS/appc.pdf | AS2: Tritium Plant Capital Cost
A3: No. | B3: Reactor | C3: Confinement Type | D3: Reactor Type | E3: Capacity [MW] | F3: Cost Type | G3: Readiness | H3: Relative/Absolute | I3: Value | J3: Unit | K3: Year | L3: Reference | M3: Study Type | N3: Source Type | O3: Comment | P3: Availability/Capacity Factor/Plasma Duration | Q3: Operational Mode | R3: Initial Tritium | S3: Contingency | T3: Decomissioning Costs/year | V3: Notes | W3: Questions & Answers to Assumptions | X3: Comparison with other Technologies | Y3: Cost Shares OCC | AE3: To be discussed | AF3: Summary (short) | AG3: Summary | AH3: Step by Step Paper Content | AI3: Most significant cost influences (short) | AJ3: Most significant cost influences | AK3: Further Cost Parameters & Assumptions (short) | AL3: Further Cost Parameters & Assumptions | AM3: Questions & Answers (short) | AN3: Questions & Answers
A4: 1 | B4: LIFE1 | C4: Inertia | D4: Indirect Drive | E4: 400 | F4: Capital Cost | G4: FOAK | H4: Absolute | I4: 6000000000 | J4: USD | K4: 2011 | L4: Anklam et al. (2011) | O4: Learning rates based on experiences from NIF but not further specified | P4: 0.5 | Q4: Steady-State (possible due to high repetition rate of laser pulses (nearly 15 per second)) | R4: - | S4: - | T4: - | V4: Monte Carlo applied 'Readiness asssumed | W4: 1. Welche Modellannahmen werden getroffen? Die LIFE-Studie trifft mehrere Modellannahmen, die darauf abzielen, ein kommerziell attraktives und reifes Fusionskraftwerk zu konzipieren: • Konzept und Technologiebasis: Das LIFE-Konzept konzentriert sich ausschließlich auf die reine Fusion und nutzt dabei die Wissenschaft und Technologie der National Ignition Facility (NIF). Dies umfasst die grundlegende Lasertechnologie (Neodym-dotierte Glas-Gain-Medien, Multipass-Architektur mit Spatial Filtering) und die Target-Physik (indirekt angetriebene Hot-Spot-Zündung). • Laserdesign und Betrieb: Das Laserdesign wird für den Kraftwerksbetrieb modifiziert, um eine kompaktere, modulare Laserarchitektur für hohe Verfügbarkeit, aktives thermisches Management für höhere Wiederholungsraten (10 bis 20 Hz) und Diodenpumpen für eine höhere Lasereffizienz (~10 % bis 20 %) zu ermöglichen. • Fusionsziele (Targets): Es wird angenommen, dass massenhaft herstellbare Fusionsziele verfügbar sind. • Phasen des Kommerzialisierungspfads: Der Pfad wird durch drei "Point Designs" beschrieben: ◦ LIFE.1: Soll 400 MW Fusionsleistung produzieren und ist darauf ausgelegt, bestehende Materialien und Technologien maximal zu nutzen. Es wird als Testbett dienen, um die erforderlichen Betriebsverfahren für ein kommerzielles Kraftwerk zu demonstrieren und Materialien sowie Prozesse in einer kontinuierlichen Fusionsumgebung zu qualifizieren. Die Inbetriebnahme wird innerhalb von 10 bis 15 Jahren nach NIF-Zündung angestrebt. Materialien werden mittels eines beschleunigten Testschemas mit höherer Strahlenschädigungsrate getestet. ◦ LIFE.2: Ein 1 GWe kommerzielles Kraftwerk, das entweder eine Neuanlage oder eine Leistungssteigerung von LIFE.1 sein könnte. Es nutzt die gleiche Lasertechnologie wie LIFE.1, jedoch fortschrittlichere, strahlungsbeständige Strukturmaterialien (Oxid-Dispersions-gehärteter Stahl – ODS-Stahl), um höhere Temperaturen und Leistungsdichten zu ermöglichen. ◦ LIFE.3: Repräsentiert eine reife LIFE-Technologie mit weiteren Verbesserungen in der Zieleffizienz, niedrigeren Fusionszielkosten und höheren Betriebstemperaturen. • Betriebsparameter (Tabelle I): Detaillierte Annahmen für die drei Point Designs umfassen: ◦ Laserenergie (1.3 MJ bis 2.4 MJ) ◦ Wiederholungsrate (konstant 14.8 Hz) ◦ Elektrischer Nettogewinn der Anlage (1.3 bis 7.0) ◦ Eigenstrombedarf (House Power Fraction: 0.77 bis 0.16) ◦ Thermodynamischer Wirkungsgrad (Thermal to Electric Efficiency: 43% bis 53%) ◦ Erste Wand-Material und Radius (LIFE.1: RAFMS, 3.7 m; LIFE.2/3: ODS-Stahl, 5.6 m / 6.2 m) ◦ Erste Wand-Neutronenlast und Lebensdauer (LIFE.1: 1.9 MW/m², 0.9 Jahre; LIFE.2/3: 4.5 MW/m², 4.5 Jahre) ◦ Fusionsausbeute und Target-Gewinn (27 MJ / Gain 21 bis 180 MJ / Gain 94) ◦ Fusionsleistung (400 MW bis 2660 MW) ◦ Verfügbarkeitsallokation (LIFE.1: 50%; LIFE.2/3: 92%). • Regulierungsrahmen: LIFE.1 und LIFE.2 werden voraussichtlich NRC-lizenziert sein, wobei LIFE.1 optional unter einer DOE-Autorisierungsbasis betrieben werden könnte. • Markteinführungszeitpunkt: Es besteht eine starke Motivation, die Kommerzialisierung bis 2030 oder früher zu erreichen, um am Ersatz veralteter Kraftwerke teilzuhaben. 2. Welche Modell- und Kostenannahmen basieren auf tatsächlichen Erfahrungswerten und welche nur Schätzungen oder Prognosen? Welche Annahmen stammen woher? Die Annahmen in der LIFE-Studie sind eine Mischung aus der Nutzung bestehender Erfahrungen und notwendigen Prognosen für eine zukünftige, noch zu entwickelnde Technologie: Modellannahmen: Basierend auf Erfahrungswerten und bestehenden Daten: • NIF-Technologie: Das Konzept nutzt die Wissenschaft und Technologie, die an der National Ignition Facility (NIF) demonstriert wird. Dies umfasst die Lasertechnologie und Target-Physik. Die NIF dient als Referenzpunkt für die Machbarkeit der grundlegenden Laser- und Fusionsprozesse. • Planung und Zeitpläne: Die Dauern für Design und Bau sind durch "previous experience in building the NIF and other large capital projects" informiert. • Marktwachstum und Anlagenlebensdauer: Die Nachfrageentwicklung in den USA wird durch Extrapolation der EIA-Prognosen bis 2100 (mit 50 % Elektrifizierung des Transportsektors bis 2050) berechnet [3, Ref. 1]. Die Annahmen für die Lebensdauer bestehender Kraftwerke (80 Jahre für Kohle/Nuklear, 60 Jahre für Erdgas) basieren ebenfalls auf Erfahrungswerten. Schätzungen oder Prognosen: • "Tenth-of-a-Kind"-Anlage: Die Annahme einer 92%igen Verfügbarkeit für eine "10th of a kind plant" (zehnte Anlage dieser Art) ist eine Prognose für den Reifegrad der modularen Architektur. Für LIFE.1 ist eine geringere Verfügbarkeit von 50% angesetzt, was dem Charakter einer Demonstrationsanlage entspricht. • Materialqualifizierung: Die Qualifizierung von ODS-Stahl (Oxid-Dispersions-gehärteter Stahl) für höhere Temperaturen und Strahlungsbeständigkeit in LIFE.1 ist eine Prognose, die durch das Testbett in LIFE.1 erreicht werden soll. • Zukünftige Effizienzsteigerungen: Für LIFE.3 werden "additional improvements in target efficiency, lower fusion target costs and higher operating temperatures" projiziert. • Marktdurchdringung: Die Rate der Marktdurchdringung von Fusion ist eine Prognose, die durch die Nachfrage und den Hochlauf der Lieferkette (Verdoppelung der Kapazität alle 5 oder 10 Jahre) begrenzt wird. • Vorteile der Frühkommerzialisierung: Die Quantifizierung von vermiedenen CO2-Emissionen (100-140 GT), hochradioaktivem Atommüll (230.000-360.000 MT) und Plutonium (3000-4000 MT) bis 2100 sind Prognosen basierend auf spezifischen Szenarien, in denen Fusion Kohle- oder Spaltanlagen ersetzt. • Kommerzialisierungszeitplan: Der Zeitplan von "roughly 12 years from project start" bis zur ersten Pilotanlage ist eine Prognose. Kostenannahmen: Basierend auf Erfahrungswerten und bestehenden Daten: • Lasersystemkosten: Werden mit einer Bottom-up-Methodik geschätzt, wobei die Einheitskosten aus Lieferantenangeboten und Daten des NIF-Projekts abgeleitet werden. • Kosten für Fusionsreaktor, Tritiumanlage und Energieumwandlungssysteme: Werden aus Studien in der Literatur entnommen (Refs. 6-10) und auf den LIFE-Betriebspunkt skaliert. ◦ Referenz 6: "Nuclear Energy Cost Data Base" für Kern- und Kohlekraftwerke. ◦ Referenz 7: "US Advanced Liquid Metal Reactor Program - Actinide Recycle Systems: 1994 Capital and Busbar Cost Estimates". ◦ Referenzen 8, 9, 10: IFE-Kraftwerksdesign-Studien (Osiris, Sombrero, Prometheus). • Kosten für Fusionsziele: Abgeleitet aus einer Studie zur Zielherstellung (Ref. 11: R. Miles, "LIFE Target Fabrication Costs," LLNL report LLNL-TR-416932 (2009)). • Indirekte Kostenfaktoren: Stammen aus den Gen IV-Kostenabschätzungsrichtlinien (Ref. 13: OECD report GIF/EMWG/2007/004 (2007)). • Kapital- und indirekte Kostendifferenziale (nukleare vs. konventionelle Systeme): Stammen aus einer General Atomic-Studie (Ref. 14: R. M. Bourque, "Fusion Reactor Cost Reductions by Employing Non-Nuclear Grade Components," 1987). • Stromgestehungskosten (COE): Berechnet unter Verwendung der Discounted Cash Flow-Methodik, wie im MIT-Bericht von 2009 beschrieben (Ref. 12: J. Deutch, "Update of the 2003 MIT Future of Nuclear Power"). • Kosten für alternative Erzeugungstechnologien: Abgeleitet aus einem aktuellen Artikel von Nicholson (Ref. 15: M. Nicholson, "How carbon pricing changes the relative competitiveness of low-carbon baseload generating technologies," 2010). Schätzungen oder Prognosen: • Gesamtkapitalkosten: Der geschätzte Bereich von $4 Mrd. bis $6 Mrd. ist eine pre-konzeptionelle Designschätzung. • Kostenreduktionen durch Lernkurven: Prognosen für Kostenreduktionen aufgrund von "manufacturing learning" für Lasersystemkomponenten, basierend auf NIF-Erfahrungen. • Nicht-Brennstoff-Betriebs-, Wartungs- und inkrementelle Kapitalkosten (O&M): Werden als Prozentsätze der gesamten Anlagenkapitalkosten angenommen und aus dem 2009 MIT-Bericht zur Zukunft der Kernkraft abgeleitet [19, Ref. 12]. • Kosten für CO2-Emissionen: Ein zugewiesener Wert von $100/MT ist ein Wert, der in politischen Diskussionen üblich ist. • Sensitivitätsparameter: Die Identifizierung von Fusionskammer-Strukturmaterial, Fusionszielkosten und Zieleffizienz als die "most highly leveraged economic parameters" basiert auf einer Monte-Carlo-Sensitivitätsanalyse, die wiederum auf Schätzungen beruht. 3. Falls externe Quellen für die Modell- und Kostenannahmen verwendet wurden – wurden diese modifiziert? Falls ja, wie? Ja, externe Quellen und Empfehlungen wurden modifiziert, skaliert oder angepasst: • LIFE-Konzept: Die Literatur beschreibt sowohl ein reines Fusions-LIFE-Konzept als auch eine Fusions-Spaltungs-Variante. Dieses Paper "deals exclusively with the pure fusion concept". Dies ist eine Modifikation/Auswahl des Anwendungsbereichs. • Lasersystemkosten: Die Lasersystemkosten werden zwar aus Lieferantenangeboten und NIF-Daten abgeleitet, es werden aber "cost reductions due to manufacturing learning" angewendet. Dies ist eine Anpassung der Rohdaten. • Kosten für Fusionsreaktor, Tritiumanlage und Energieumwandlungssysteme: Diese Kosten werden aus Literaturstudien entnommen und "scaled to the LIFE operating point using standard scaling relations". Dies ist eine direkte Modifikation durch Skalierung. • Nicht-Brennstoff-O&M und inkrementelle Kapitalkosten: Werden als Prozentsätze der gesamten Anlagenkapitalkosten angenommen, wobei diese Prozentsätze aus dem MIT-Bericht abgeleitet wurden. Hier wird die Methode der prozentualen Skalierung aus einer externen Quelle angewendet. 4. Wie lautet die Annahme zu Lernraten? Die Studie geht davon aus, dass es für die Komponenten des Lasersystems Kostenreduktionen aufgrund von "manufacturing learning" geben wird. Die verwendeten Lernraten wurden durch "experience with NIF" informiert. Spezifische prozentuale Lernraten werden in diesem Dokument jedoch nicht angegeben. 5. Wie wurden die Annahmen zu den Lernraten hergeleitet bzw. von wo stammen diese Annahmen? Die Annahmen zu den Lernraten wurden aus Erfahrungen mit dem NIF-Projekt hergeleitet. Der Kontext ist, dass viele der Lasersystemkomponenten in großen Mengen produziert werden, was die Anwendung von Lernkurven zur Schätzung von Kostenreduktionen rechtfertigt. Die Studie geht implizit davon aus, dass eine Industrie aufgebaut wird, die von Skaleneffekten und Lernkurven profitiert. 6. Wird offengelegt, ob die Kostenabschätzung auf einem Bottom-up-, Top-down- oder hybriden Ansatz basiert? Ja, es wird offengelegt, dass ein hybrider Ansatz verwendet wird: • Die Lasersystemkosten werden explizit "using a bottom up methodology" geschätzt. • Die Kosten für den Fusionsreaktor, die Tritiumanlage und die Energieumwandlungssysteme werden "from studies in the literature and scaled to the LIFE operating point using standard scaling relations" entnommen. Dies ist eher ein Top-down- oder analoger Skalierungsansatz. • Insgesamt ist es also eine Kombination aus Bottom-up (Laser) und Top-down/Analog-Skalierung (andere Systeme). 7. Beruht die Kostenherleitung auf physikalischen und technologischen Werten? Ja, die Kostenherleitung beruht maßgeblich auf physikalischen und technologischen Werten: • Lasersystemkosten: Basieren auf Lieferantenangeboten und NIF-Projektdaten, die die spezifische Lasertechnologie widerspiegeln. • Skalierung der Fusionssysteme: Die Kosten für den Fusionsreaktor, die Tritiumanlage und die Energieumwandlungssysteme werden auf den "LIFE operating point" skaliert. Dieser Betriebspunkt ist durch physikalische und technologische Parameter definiert, wie Laserenergie, Wiederholungsrate, Fusionsausbeute, Target-Gewinn, Fusionsleistung, Wirkungsgrade, Material der ersten Wand und Neutronenlast. • Fusionszielkosten: Stammen aus einer Studie zur Zielherstellung [19, Ref. 11], die die Technologie und den Prozess der Fusionszielproduktion bewertet. • Anlagenverfügbarkeit: Die hohe Verfügbarkeit (92 %) wird durch die modulare Architektur des Anlagendesigns ermöglicht. Dies ist eine technologische Entscheidung mit direkter wirtschaftlicher Auswirkung. • Wichtige Kostentreiber: Die Monte-Carlo-Sensitivitätsanalyse identifiziert das Fusionskammer-Strukturmaterial, die Fusionszielkosten und die Zieleffizienz als die wirtschaftlich wichtigsten Parameter. Dies sind alles direkte physikalische und technologische Eigenschaften und Leistungen des LIFE-Systems. 8. Werden Materialkosten und Komponentenkosten separat ausgewiesen? In der vorliegenden Quelle werden Materialkosten und Komponentenkosten nicht in detaillierten Tabellen separat ausgewiesen, wie es beispielsweise in einigen anderen Studien (z.B. STARFIRE aus unserer früheren Konversation) der Fall ist. Die Studie erwähnt: • "Laser system costs are estimated using a bottom up methodology. Unit costs are derived from vendor quotes and data from the NIF project". Hier sind die "Unit costs" wahrscheinlich integrierte Komponentenkosten. • Das Fusionskammer-Strukturmaterial wird als wichtigster wirtschaftlicher Parameter genannt, was auf Materialkosten hindeutet. • Die Fusionszielkosten werden als weitere wichtige Parameter genannt, was die Kosten des verbrauchten "Materials" oder der "Komponente" (des Targets) darstellt. Es gibt keine detaillierten Aufschlüsselungen nach Masse, Kosten pro kg oder Materialtyp in dieser Quelle. 9. Bezieht sich die Studie auf ein Energiesystem (z. B. Integration, Vergleich mit anderen Technologien) oder ist sie rein bezogen auf die Kosten des Kraftwerks und des Reaktors? Die Studie bezieht sich eindeutig auf ein umfassendes Energiesystem und geht weit über eine reine Kostenanalyse des Kraftwerks und des Reaktors hinaus. • Quantifizierung der Vorteile: Die Studie quantifiziert die Vorteile von Fusionsenergie im Hinblick auf die Vermeidung von Kohlenstoffemissionen, Atommüll und Plutoniumproduktion innerhalb des US-Stromerzeugungssystems. • Relevanz für den Energiemarkt: Sie adressiert den Bedarf an kohlenstoffarmer Grundlaststromerzeugung, der durch das Alter der bestehenden Kraftwerke und den steigenden Strombedarf entsteht. • Wirtschaftliche Wettbewerbsfähigkeit: Die Studie bewertet, ob Fusionsenergie "competitive with other low-carbon energy sources" sein kann. Sie vergleicht die Stromgestehungskosten (COE) von LIFE mit anderen Grundlast-Energiequellen und fossilen Brennstoffen (unter Berücksichtigung von Kohlenstoffkosten). • Marktdurchdringung: Es wird die Rate der Marktdurchdringung von Fusion analysiert, die durch Nachfrage und den Aufbau der Lieferkette begrenzt ist. • Politische Implikationen: Es wird ein Wert von $100/MT für CO2-Emissionen angenommen, der in politischen Diskussionen relevant ist. Die Studie diskutiert auch Proliferationsbedenken im Zusammenhang mit Plutoniumlagerung. • Gesamtwirtschaftliche Bedeutung: Die Studie bewertet die "Benefits of Early Commercialization of Fusion Energy" und die "Implications for national and global security and environment". 10. Welche Kostenreduktionspotenziale oder wirtschaftlichen Optimierungsansätze werden thematisiert? Die Studie thematisiert mehrere Kostenreduktionspotenziale und wirtschaftliche Optimierungsansätze: • Economies of Scale: Es gibt eine natürliche Größenvorteil (economy of scale) bei LIFE, da die Effizienz der Umwandlung von Laserenergie in Fusionsenergie steigt, wenn das Kraftwerk auf eine größere elektrische Leistung skaliert wird. Dies führt zu einer reduzierten Kapitalintensität ($/kW) für größere Anlagen. Dies motiviert das Design größerer Anlagen. • Verbesserungen der Zieleffizienz: Es wird erwartet, dass es "additional improvements in target efficiency" geben wird, die zur Kostenreduktion beitragen. • Niedrigere Fusionszielkosten: Die Prognose von "lower fusion target costs" ist ein weiteres Potenzial zur Kostenreduktion. • Höhere Betriebstemperaturen: Projekte von "higher operating temperatures" werden als Kostenoptimierung und Effizienzsteigerung gesehen. • Fertigungslernen (Manufacturing Learning): Es werden Kostenreduktionen aufgrund von Fertigungslernen für Lasersystemkomponenten erwartet, da diese in großen Mengen produziert werden. • Modulare Architektur: Die modulare Architektur der Anlage ermöglicht eine hohe Verfügbarkeit (92 %), was ein Schlüsselfaktor für niedrige Stromgestehungskosten ist. • Entwicklung fortschrittlicher Materialien: Die Entwicklung und Qualifizierung von Oxid-Dispersions-gehärtetem Stahl (ODS-Stahl) ermöglicht höhere Temperaturen und Leistungsdichten, was die Wirtschaftlichkeit verbessert. • Parallele Entwicklung: Die Target-Entwicklung kann parallel zu anderen Entwicklungsaktivitäten durchgeführt werden, wobei Fortschritte durch Tests an der NIF validiert werden können. Dies beschleunigt die Entwicklung und reduziert Risiken. • Maximale Nutzung bestehender Technologie: Für die Demonstrationsanlage LIFE.1 wird die maximale Nutzung bestehender Materialien und Prozesse vorgeschlagen, um den F&E-Bedarf zu minimieren. 11. Was sind die signifikantesten Kostentreiber und ökonomischen Herausforderungen laut Studie? Die Studie identifiziert die folgenden signifikantesten Kostentreiber und ökonomischen Herausforderungen, insbesondere durch ihre Sensitivitätsanalyse: • Fusionskammer-Strukturmaterial: Dies ist der "most highly leveraged economic parameter" (der am stärksten wirkende Wirtschaftsparameter). Dies unterstreicht die Herausforderung und die Bedeutung der laufenden Entwicklungen bei Materialien wie ODS-Stahl, um höhere Temperaturen und Strahlungsbeständigkeit zu erreichen. • Fusionszielkosten und Zieleffizienz: Diese beiden sind die "next two most highly leveraged parameters". Die Kosten für die Herstellung der Fusionsziele und deren Effizienz bei der Energieerzeugung sind entscheidend für die Wirtschaftlichkeit. • Pre-konzeptionelles Designniveau: Die aktuellen Kostenschätzungen basieren auf einem "pre-conceptual design level", was bedeutet, dass noch "additional work is needed". Dies impliziert, dass Unsicherheiten und potenzielle Kostensteigerungen im weiteren Designprozess bestehen. • Technisches Risiko und aggressiver Zeitplan: Der vorgeschlagene Kommerzialisierungsansatz birgt "technical risk and is aggressive". Dies stellt eine Herausforderung dar, die einen nationalen Konsens und die Zusammenarbeit von Industrie, Forschungseinrichtungen, Regierung und Aufsichtsbehörden erfordert. • Kapazitätsaufbau der Lieferkette: Die Rate der Marktdurchdringung von Fusion wird durch den "ramp up of the supply chain needed to build fusion plants" begrenzt, was eine logistische und wirtschaftliche Herausforderung darstellt. • Verpasste Marktopportunitäten: Die Studie betont die Dringlichkeit der Frühkommerzialisierung. Wenn die Recapitalisierung des Stromnetzes ohne Fusion abgeschlossen ist, sind die Marktchancen auf die Deckung des steigenden Strombedarfs begrenzt, was die potenziellen Vorteile der Fusion erheblich verringert. Dies ist eine ökonomische Herausforderung im Hinblick auf den "Window of Opportunity". | X4: Basierend auf der LIFE-Studie von Anklam et al. (2011) wird ein Vergleich mit den Kosten anderer Energieerzeugungen durchgeführt, und es lassen sich folgende Ergebnisse festhalten: **Vergleich mit anderen Energieerzeugungen:** 1. **Verglichene Technologien:** * Die Stromgestehungskosten (Cost of Electricity, COE) von LIFE werden mit denen **anderer kohlenstoffarmer Stromerzeugungstechnologien ("other low-carbon electrical energy technologies")** verglichen. * Des Weiteren erfolgt ein Vergleich mit **anderen Grundlastenergiequellen ("other base load energy sources")**. * Schließlich werden die Kosten auch mit **fossiler Stromerzeugung ("fossil fuel generation")** verglichen, wobei hier ein variabler **CO2-Preis ("cost of carbon")** berücksichtigt wird. * Die Kosten für diese alternativen Technologien wurden aus einem aktuellen Papier von Nicholson abgeleitet [20, Ref. 15]. 2. **Ergebnis des Vergleichs:** * Die geschätzten Stromgestehungskosten für **LIFE sind vergleichbar ("comparable") mit denen anderer kohlenstoffarmer Grundlastenergiequellen**. * Die Kosten für LIFE sind **geringer ("less than") als die Kosten der fossilen Stromerzeugung, wenn die CO2-Kosten 50 bis 100 US-Dollar pro Tonne (MT) übersteigen**. **Kontext der LIFE-Kosten:** * Die geschätzten Stromgestehungskosten für LIFE umfassen eine Bandbreite: Das **obere Ende** der angegebenen Spanne bezieht sich auf die **LIFE.1-Anlage (First-of-a-Kind)**, während das **untere Ende** der Spanne dem **LIFE.3-System** (repräsentiert eine ausgereifte LIFE-Technologie) entspricht. * Es wird betont, dass die LIFE-Kosten auf einem **vorkonzeptionellen Design ("pre-conceptual design")** basieren, die Ergebnisse aber indikativ sind und das wirtschaftliche Potenzial der LIFE-Technologie aufzeigen. * Die Studie kommt zu dem Schluss, dass die **Wirtschaftlichkeit von LIFE gut mit der anderer kohlenstoffarmer Technologien vergleichbar ist**. Dieser Vergleich wird visuell in **Abbildung 4 ("Economic comparison to other low carbon technologies")** dargestellt. | Y4: n/a
A5: 2 | B5: LIFE2 | C5: Inertia | D5: Indirect Drive | E5: 2200 | F5: Capital Cost | G5: NOAK | H5: Absolute | I5: =(6000000000+4000000000)/2 -> 5000000000 | J5: USD | K5: 2011 | L5: Anklam et al. (2011) | O5: Average value between 4 and 6 billion USD; Learning rates based on experiences from NIF but not further specified | P5: 0.92 | Q5: Steady-State (possible due to high repetition rate of laser pulses (nearly 15 per second)) | R5: - | S5: - | T5: -
A6: 3 | B6: LIFE3 | C6: Inertia | D6: Indirect Drive | E6: 2660 | F6: Capital Cost | G6: 10th-OAK | H6: Absolute | I6: 4000000000 | J6: USD | K6: 2011 | L6: Anklam et al. (2011) | O6: Learning rates based on experiences from NIF but not further specified | P6: 0.92 | Q6: Steady-State (possible due to high repetition rate of laser pulses (nearly 15 per second)) | R6: - | S6: - | T6: -
A7: 176 | B7: PPCS-A | C7: Magnetic | D7: Tokamak | E7: 1546 | F7: Capital Cost | G7: 10th-OAK | H7: Relative | I7: 6400 | J7: EUR/kW | K7: 2005 | L7: Ward / in Maisonnier et al. (2005) | O7: 6% discount rate; 40 years lifetime; Abgelesen; Fusion power: 5 GW; 10th of a kind plant with a corresponding cost reduction factor of 0.65 for fusion specific items; based on conventional superconducting technology, Nb3Sn for the toroidal field and NbTi for the poloidal field. Advances in superconductors, to lower cost materials and to high temperature superconductors are expected to reduce these costs but this is an uncertain issue; Divertor every 2 years; Blanket every 5 years replacement | P7: 0.75 | Q7: Steady-State with possibility for load-following by decrasing el. Output up to 50% ("Both from the plasma physics and technology viewpoints, it would be feasible to reduce the electrical output by about fifty percent.") | R7: - | S7: - | T7: - | V7: Report too long advanced conceptual Tokamak fusion power reactor | W7: Die Beantwortung der folgenden Fragen basiert ausschließlich auf der Studie zum **UWMAK-III Conceptual Tokamak Fusion Power Reactor** von Conn und Kuo (1976). --- ### 1. Welche Modellannahmen werden getroffen? Die Modellannahmen betreffen hauptsächlich die Extrapolation der Technologie und die Spezifikationen des Reaktors und des Energieumwandlungssystems: * **Technologische Extrapolation:** Design-Entscheidungen stellen **"vernünftige Extrapolationen der gegenwärtigen Technologie"** dar, die im Kontext des **"allgemeinen Zeitrahmens, der für die breite praktische Anwendung der kontrollierten Fusion vorgesehen ist"**, getroffen werden. * **Strukturmaterial:** Als primäres Strukturmaterial wird die Molybdän-basierte Legierung **TZM** (Titan-Zirkonium-Molybdän) gewählt. * **Magnete:** Die Toroidalfeldmagnete verwenden den Supraleiter **NbTi** mit **Aluminium (Al)** als Stabilisator und einer hochfesten Aluminiumlegierung als Strukturmaterial. * **Betriebsleistung:** Der Reaktor ist darauf ausgelegt, kontinuierlich **$4735 \text{ MW(th)}$** und **$1985 \text{ MW(e)}$ netto** zu erzeugen. Die angestrebte Nettoanlageneffizienz beträgt **$41.9\text{ \%}$** (Ziel: ca. $40\text{ \%}$). * **Pulsbetrieb:** Es wird angenommen, dass der Tokamak ein **gepulstes Plasma-Gerät** ist. Der Zyklus besteht aus einer Brennzeit von **$1800 \text{ Sekunden}$** und einer Auszeit von $\text{100 Sekunden}$ (Start-up, Shutdown, Pumpout/Refill), was zu einem Duty Factor von **$0.947$** führt. * **Kontinuierlicher Betrieb:** Aufgrund des gepulsten Betriebs ist die Verwendung eines **thermischen Energiespeichers** (*thermal storage*) erforderlich, um eine unterbrechungsfreie, konstante elektrische Leistung zu liefern. * **Blanket-Design:** Das Design besteht aus einer **zwei Zonen** (*two-zone*) Blanketanordnung (heliumgekühlte innere Zone als Schild, lithiumgekühlte äußere Zone zur Tritiumzucht). Die Lebensdauer der inneren Strukturwand ist auf **Anlagenlebensdauer** ausgelegt, die äußere Wand muss aufgrund der Strahlenbelastung **periodisch ersetzt** werden (geschätzte Lebensdauer: **ca. 2 Jahre**). * **Kühlmittelbedingungen:** Die Turbine Inlet Temperature (TIT) wird auf **$871^\circ\text{C}$ ($1600^\circ\text{F}$)** festgelegt, basierend auf den prognostizierten Blanket-Fähigkeiten. Der Turbineneinlassdruck beträgt **$1000 \text{ psia}$**. ### 2. Welche Modell- und Kostenannahmen basieren auf tatsächlichen Erfahrungswerten und welche nur Schätzungen oder Prognosen? Welche Annahmen stammen woher? Die Studie kombiniert bekannte Technologie mit notwendigen Extrapolationen: | Annahme | Basis (Erfahrung/Prognose) | Herkunft/Bezug | | :--- | :--- | :--- | | **Materialwahl (TZM)** | **Prognose/Extrapolation:** Basierend auf der gewünschten **hohen Betriebstemperatur** und der erwarteten Kompatibilität mit Helium und flüssigem Lithium. | Wird als "vernünftige Extrapolation der gegenwärtigen Technologie" gewählt. | | **Turbineneinlasstemperatur** | **Prognose/Extrapolation:** Die gewählte $\text{TIT}$ ($871^\circ\text{C}$) liegt **über dem damaligen Stand der Technik** ($760^\circ\text{C}$ bis $815^\circ\text{C}$). Man erwartet, dass die Temperatur bis zum Jahr 2010 um $300\text{–}400^\circ\text{C}$ steigen wird. Die Wahl basiert auf **"projizierten Blanket-Fähigkeiten"**. | Interne Systemanalyse und externe Entwicklungsprognosen. | | **Magnet-Stabilisator (Al)** | **Prognose/Extrapolation:** Die Verwendung von reinem $\text{Aluminium}$ reduziert die notwendige Stabilisatormenge um den Faktor $2$ bis $5$ im Vergleich zu Kupfer. Dies beruht auf Experimenten der University of Wisconsin, die zeigten, dass verstärktes $\text{Al}$ seine niedrige Resistivität auch unter Stress behält. | University of Wisconsin-Experimente. | | **Geschlossener Gaskreislauf** | **Erfahrung/Basis:** Das Design des **Regenerators** (88 \% Effektivität) basiert auf der Nutzung der **Leistungs- und Kostenmerkmale von Komponenten- und Designstudien** für $100\text{–}600 \text{ MW(e)}$ geschlossene Gasturbinen-Systeme. Die Turbomaschinen-Auslegung basiert auf **"vergangenen Erfahrungen"** (*past experience*). | Vergangene Studien von $100\text{–}600 \text{ MW(e)}$-Anlagen. | ### 3. Falls externe Quellen für die Modell- und Kostenannahmen verwendet wurden – wurden diese modifiziert? Falls ja, wie? Die gesamte konzeptionelle Designstudie ist eine **Modifikation und Extrapolation** vorhandener Daten und Technologien, um ein höheres Leistungsniveau zu erreichen: * **Modifikation der Design-Parameter:** Die Betriebsparameter der Helium-Gasturbine (Temperatur, Druck, Druckverhältnis, Regenerator-Effektivität) wurden **nicht direkt** übernommen, sondern durch **parametrische Analysen** und **Trade-off-Studien** zwischen Effizienz und Kosten ermittelt. * **Anpassung des Kreislaufs:** Die Komplexität des Tokamak-Designs (gepulster Betrieb, Zwei-Zonen-Blanket, Tritiumzucht) erforderte die Entwicklung eines komplexen Integrationsschemas (z. B. drei separate Kreisläufe, Zwischenwärmetauscher für Tritiumeindämmung). Die Referenzkonfiguration (mit einer Zwischenkühlstufe und Regeneration) wurde aus sechs Kandidaten ausgewählt, um die spezifischen $\text{UWMAK-III}$-Anforderungen zu erfüllen. * **Größenänderung:** Die Anlage ist eine **"wesentlich reduzierte Größe"** im Vergleich zu den Vorgängerstudien $\text{UWMAK-I}$ und $\text{UWMAK-II}$ (Hauptradius von 13 m auf 8.1 m), ermöglicht durch die Erhöhung der Neutronenwandbelastung und die Nutzung von nicht-zirkulärem Plasma. ### 4. Wie lautet die Annahme zu Lernraten? Die vorliegende Quelle **nennt keine spezifischen Zahlenwerte** für Lernraten, Lernkurven oder Produktionslernen, wie sie in den Konzepten $\text{10th-OAK}$ oder $\text{Mature NOAK}$ verwendet werden. Der Fokus liegt auf den Kapitalkosten ($\text{\$/kW}$) des gesamten Kraftwerks als Hauptziel. ### 5. Wie wurden die Annahmen zu den Lernraten hergeleitet bzw. von wo stammen diese Annahmen? Da die Quelle keine expliziten Lernraten nennt, kann diese Frage nicht beantwortet werden. ### 6. Wird offengelegt, ob die Kostenabschätzung auf einem Bottom-up-, Top-down- oder hybriden Ansatz basiert? Die Studie **offenbart nicht** explizit, ob ein Bottom-up-, Top-down- oder hybrider Ansatz verwendet wird. Die Methodik ist jedoch stark **Bottom-up-orientiert**: Es werden die **physikalischen Zwänge** des Reaktors (Temperatur, Leistung, Kühlung) als Input verwendet, um die **geforderten Spezifikationen und Dimensionen** der Hauptkomponenten (Turbinen, Wärmetauscher, Rohre) zu definieren. Anschließend wird die **Kapitalkosten der gesamten Anlage ($\text{\$/kW}$)** als wichtigstes Kriterium genannt. ### 7. Beruht die Kostenherleitung auf physikalischen und technologischen Werten? **Ja**, die gesamte ökonomische Analyse und die Auslegung beruhen auf physikalischen und technologischen Werten und Zwängen: * **Effizienz vs. Kosten:** Die Auswahl der Betriebsparameter (Druckverhältnis, Regeneration) erfolgt durch **Trade-offs zwischen thermischer Effizienz und der Komplexität/Kosten** der Komponenten. * **Physische Beschränkungen:** Die **Turbineneinlasstemperatur** (*Turbine Inlet Temperature*) ist die wichtigste ökonomische Variable, wird jedoch durch die **Temperaturfähigkeit des Blankets** (*blanket capability*) begrenzt. * **Kompaktbauweise vs. Druck:** Ein **höherer Turbineneinlassdruck** ist wünschenswert, um **kleinere Anlagenteile** und bessere Wärmeübergangskoeffizienten zu erhalten. Der gewählte Druck von $1000 \text{ psia}$ war für die geplante $\text{500–600 MW(e)}$ Turbomaschinenkapazität **zwingend erforderlich**. ### 8. Werden Materialkosten und Komponentenkosten separat ausgewiesen? **Nein.** Die Studie enthält **keine detaillierte Aufschlüsselung** von Materialkosten oder Gesamtkomponentenkosten. Sie konzentriert sich auf die **relative Optimierung** des Kreislaufs und darauf, dass die **Kapitalkosten der gesamten Anlage ($\text{\$/kW}$) der wichtigste Faktor** sind. Es werden jedoch Designentscheidungen getroffen, die auf impliziten Kostenannahmen beruhen, wie die Verwendung von **Aluminium** anstelle von Kupfer als Magnetstabilisator, um die benötigte Materialmenge zu reduzieren und das Gewicht zu senken. ### 9. Bezieht sich die Studie auf ein Energiesystem (z. B. Integration, Vergleich mit anderen Technologien) oder ist sie rein bezogen auf die Kosten des Kraftwerks und des Reaktors? Die Studie bezieht sich primär auf den **Reaktor (Tokamak) und das angeschlossene Kraftwerkssystem** (insbesondere das Helium-Gasturbinen-System). Sie berücksichtigt jedoch Randbedingungen der **Systemintegration** und des **zukünftigen Energiemarktes**: * **Umwelt- und Systemintegration:** Das Design berücksichtigt, dass die **Trockenkühlung** (*dry cooling*) für die Abwärmeabfuhr möglicherweise zwingend erforderlich sein wird. Das geschlossene Gasturbinensystem ist dafür **ökonomisch besser anpassbar** als ein Dampfkraftwerk. Es muss auch **kompatibel** mit bestehenden Stromnetzen (3600 U/min, $60 \text{ Hertz}$) sein. * **Technologievergleich:** Die Autoren erwarten, dass technologische Fortschritte im geschlossenen Helium-Gasturbinen-System, die für Fusion entwickelt wurden, direkt auf die **zukünftige Energieerzeugung** durch **fossile, Spalt- und Solaranlagen** anwendbar sein werden. Die Effizienz ($\text{41.9 \%}$) wird explizit mit früheren Fusionsanlagen ($\text{UWMAK-I}$, $\text{UWMAK-II}$, Princeton) verglichen. ### 10. Welche Kostenreduktionspotenziale oder wirtschaftlichen Optimierungsansätze werden thematisiert? Folgende Ansätze zur Kostenreduzierung werden verfolgt oder thematisiert: * **Skalierung und Standardisierung:** Verwendung von **drei identischen $585 \text{ MW(e)}$ Leistungsumwandlungsschleifen** (*three identical loops*), was die Komponentenkosten senken und die Wartung vereinfachen soll. * **Kompakte Bauweise:** Signifikante **Größenreduzierung** des Kerns (von 13 m auf 8.1 m Hauptradius) durch nicht-zirkuläres Plasma und höhere Wandbelastung. * **Erhöhte Effizienz:** Erhöhung der **thermischen Gesamteffizienz** auf $41.9\text{ \%}$ durch die Verwendung von $\text{TZM}$ für höhere Betriebstemperaturen. * **Minimierung der Komplexität:** Die $\text{TZM}$-Konstruktion des inneren Blankets ist auf **Anlagenlebensdauer** ausgelegt, um die Notwendigkeit eines Austauschs in diesem schwer zugänglichen Bereich zu eliminieren. * **Gezielter Materialeinsatz:** Nutzung von **Aluminium** für die Magnetstruktur zur Gewichtsreduzierung (auf etwa ein Drittel des Gewichts von 316 Edelstahl) und Kostensenkung. ### 11. Was sind die signifikantesten Kostentreiber und ökonomischen Herausforderungen laut Studie? Die signifikantesten ökonomischen Herausforderungen sind: * **Kapitalkosten:** Die **Kapitalkosten der gesamten Kraftwerksanlage ($\text{\$/kW}$)** sind das wichtigste Entscheidungskriterium. * **Blanket-Temperatur als Limit:** Die **Temperaturfähigkeit des Blanket-Materials** ist der begrenzende Faktor für die gesamte Anlagenleistung und Effizienz, nicht die Gasturbinen-Technologie. * **Thermische Energiespeicherung:** Die inhärent **gepulste Natur des Tokamaks** macht die Entwicklung eines **funktionsfähigen Energiespeichersystems** (*viable energy storage system*) zur Gewährleistung des kontinuierlichen Betriebs **zwingend erforderlich**. Das Versagen, ein solches System zu entwickeln, könnte die Implementierung der Anlage **behindern**. * **Komplexität und Tritiumeindämmung:** Die Notwendigkeit eines **Zwischenwärmetauschers** aufgrund der Tritiumzucht im Lithium-Blanket führt zu einer **niedrigeren Turbineneinlasstemperatur** und damit zu einer reduzierten Effizienz und erhöhter Komplexität. * **Wartung des Divertors und des Blankets:** Das Divertor-Auffangblech (*sacrificial wall*) und die äußere Blankethülle müssen **häufig ausgetauscht** werden (z. B. Divertorblech alle 17 Stunden, äußere Blanketwand alle 2 Jahre), was die Wartungskosten erhöht. | X7: Die Kostenvergleiche der Fusionsreaktoren mit anderen Energieerzeugungstechnologien, die in den Quellen diskutiert werden (sowohl in der neuen Quelle als auch in der Gesprächshistorie), führen im Allgemeinen zu dem Ergebnis, dass **Fusionsenergie nur dann wettbewerbsfähig** ist, wenn **zukünftige, optimierte (10th-OAK oder Mature NOAK) Designs** realisiert werden, die auf **zukünftigen Projektionen** von Kosten und technologischem Fortschritt basieren. ### 1. Ergebnis des Kostenvergleichs Die Ergebnisse des Vergleichs sind nur dann positiv, wenn die Fusionsdesigns stark optimiert sind und von Lernkurven profitieren: | Reaktorkonzept / Studie | Ergebnis des Vergleichs | Vergleichsbasis | | :--- | :--- | :--- | | **UWMAK-III (1976)** | Der Fokus lag auf der **internen Optimierung** des $\text{\$/kW}$-Kapitalkostenziels und der Effizienz (Nettoeffizienz 41,9 \%). Es wurde **keine direkte quantitative Kostenvergleichsaussage** mit fossilen oder Spaltkraftwerken getroffen. Die Studie erwartet, dass die technologischen Fortschritte, die für die Helium-Gasturbinen benötigt werden, auch in zukünftigen fossilen, Spalt- und Solaranlagen zur Anwendung kommen. | Zukünftige Technologie | | **Helsley and Burke (2014)** | Ein voll ausgelastetes **großes HIF-System** (30+ $\text{GWe}$) wäre **wirtschaftlich tragfähig** (*economically viable*) und könnte Energie zu **etwa der Hälfte der Kosten** (*roughly one half the cost*) der derzeitigen konventionellen fossilen oder Spalt-Systeme produzieren. | Aktuelle konventionelle Kosten | | **Lerede et al. (2023)** | Fusionsanlagen können nur **durch einen robusten Lernprozess** und die Entwicklung zu **"reifen Fusionskraftwerken"** (*mature fusion power plants*) mit **anderen kohlenstoffarmen Infrastrukturen wie modernen Leichtwasserreaktoren konkurrieren** [Lerede et al. (2023)]. | Zukünftige kohlenstoffarme Alternativen | | **Prometheus (Moir, 1992)** | Erreichte ein niedriges Stromgestehungspreis (COE) von **62,6 bis 72,0 mills/kWh** (1991$) und erfüllte damit die **niedrigeren kommerziellen Ziele** [Moir (1992)]. | Kommerzielle Ziele | ### 2. Vergleich mit historischen oder zukunftsgerichteten Projektionen Alle Fusionsstudien, die die Kosten mit externen Energiequellen vergleichen, stützen sich **fast ausschließlich auf zukunftsgerichtete Projektionen** und **hochgerechnete Werte** für die Fusionsanlage. * **Extrapolation der Technologie:** Das $\text{UWMAK-III}$-Design basiert auf **"vernünftigen Extrapolationen der gegenwärtigen Technologie"** (*reasonable extrapolations of present technology*). Die maximal zulässige Turbineneintrittstemperatur ($871^\circ\text{C}$ / $1600^\circ\text{F}$) wurde gewählt, basierend auf den erwarteten **zukünftigen Entwicklungen** in der Blankettstruktur. Die Technologie wird im Kontext des **"allgemeinen Zeitrahmens, der für die breite praktische Anwendung der kontrollierten Fusion vorgesehen ist"**, betrachtet. * **Wettbewerb des zukünftigen Marktes:** Studien wie die von Krakowski (1995) analysieren die Richtung für **"wettbewerbsfähige MFE-Kraftwerke"** (*competitive MFE power plants*), die einen **zukünftigen Marktzug** (*future market pull*) aufweisen müssen, und vergleichen die Kosten der Fusionsanlagen in ihrer **"reifen Technologie"**-Phase ($10\text{th-OAK}$ oder $\text{100th-OAK}$) [Krakowski (1995)]. * **Lernkurvenannahmen:** Die ökonomische Wettbewerbsfähigkeit in Studien wie Lerede et al. (2023) hängt von einer angenommenen **Kostenreduzierung** durch technologisches Lernen (z. B. 30 % Kapitalminderung für die $\text{10th-OAK}$) ab [Lerede et al. (2023)]. * **Extrapolation des Zeitrahmens:** Die Prometheus-Studien (Moir, 1992) beruhen auf einer Extrapolation der Physik, Technologie und Ökonomie um **etwa 30 bis 40 Jahre** [Moir (1992)]. Zusammenfassend lässt sich sagen, dass der Kostenvergleich nicht mit den historischen, heutigen Kosten von Fusionsanlagen erfolgt, sondern mit der **projektierten, optimierten COE-Leistung der zukünftigen Fusionsreaktoren** im Vergleich zu den **zukünftigen oder gegenwärtigen Kosten von Konkurrenztechnologien** (Spalt-, Solar- oder Fossil-Kraftwerke). | Y7: 25% buildings, 35% reactor plant equipment, 25% turbine plant, 12% electric plant equipment, 3% miscellaneous items (10& toroidal field magnets of reactor plant equipment)
A8: 177 | B8: PPCS-B | C8: Magnetic | D8: Tokamak | E8: 1332 | F8: Capital Cost | G8: 10th-OAK | H8: Relative | I8: 5500 | J8: EUR/kW | K8: 2005 | L8: Ward / in Maisonnier et al. (2005) | O8: 6% discount rate; 40 years lifetime; Abgelesen; Fusion power: 3.6 GW; 10th of a kind plant with a corresponding cost reduction factor of 0.65 for fusion specific items; based on conventional superconducting technology, Nb3Sn for the toroidal field and NbTi for the poloidal field. Advances in superconductors, to lower cost materials and to high temperature superconductors are expected to reduce these costs but this is an uncertain issue.; Divertor every 2 years; Blanket every 5 years replacement | P8: 0.75 | Q8: Steady-State with possibility for load-following by decrasing el. Output up to 50% ("Both from the plasma physics and technology viewpoints, it would be feasible to reduce the electrical output by about fifty percent.") | R8: - | S8: - | T8: - | V8: Readiness for Advanced and Highly Advanced assumed since being constructed after 10th-OAK 10th-OAK 20 years after FOAK "capital costs" | W8: 1. **Welche Modellannahmen werden getroffen?** Die Studie verwendet eine **Realoptionsbewertung** des Fusionsenergie-F&E-Programms. Dabei werden folgende Modellannahmen getroffen: * **Realoptionsmodelle:** Es wird ein grundlegendes **Investitionsoptionsmodell vom Black–Scholes-Typ** und ein komplexeres **Compound Real R&D Option Modell** verwendet, das die mehrstufige Natur des Programms abbildet. Zusätzlich wird ein **Fuzzy Real Option Modell** entwickelt, das unsichere Parameter (Kosten, Nutzen, Zeitplanung) mit **trapezförmigen oder dreieckigen Fuzzy-Zahlen** darstellt, um die Ungenauigkeit von Informationen zu berücksichtigen. * **Strategien:** Es werden zwei Entwicklungsstrategien verglichen: * **"Baseline"**: Ein relativ moderates Tempo der Fusionsforschung, -entwicklung, -demonstration und -bereitstellung, bei der nach ITER/IFMIF nur ein DEMO-Reaktor gebaut wird. * **"Accelerated"**: Eine beschleunigte Demonstration und massive Bereitstellung, die den gleichzeitigen Bau von zwei oder mehr DEMO-Reaktoren annimmt. Dies führt zu höheren F&E- und DEMO-Kosten, aber zu einer früheren Verfügbarkeit der Technologie. * **Szenarien:** Für die **deterministische Analyse** werden drei Szenarien entwickelt: **pessimistisch ("A"), intermediär ("B") und optimistisch ("C")**. * **Probabilistische Simulation:** Zusätzlich zu den deterministischen Szenarien werden Berechnungen in einem **stochastischen probabilistischen Setting** durchgeführt, das zufällige Schwankungen der Hauptparameter (Dauer, Kosten, Einnahmen, Diskontsatz) innerhalb vordefinierter Bereiche zulässt und spezifische Erfolgswahrscheinlichkeiten für jede Programmphase zuweist. * **Zeithorizont:** Die Analyse erstreckt sich über einen sehr langen Zeitraum, der über 100 Jahre hinausgeht, wobei die Einsatzphase der Fusionskraftwerke (FPPs) von **2051 bis 2100** angesetzt wird. * **Diskontierung:** Im deterministischen Fall wird ein **konstanter Diskontsatz von 4%** verwendet (mit Sensitivitätsanalysen von 2-6%), während im probabilistischen Fall **unsichere stochastische Diskontsätze im Bereich von 3% bis 5%** angenommen werden. Für das Real-Options-Modell wird ein **risikofreier Zinssatz von 2,25%** verwendet. 2. **Welche Modell- und Kostenannahmen basieren auf tatsächlichen Erfahrungswerten und welche nur Schätzungen oder Prognosen? Welche Annahmen stammen woher?** * **Allgemein:** "Die meisten der angenommenen Eingaben sind **Schätzungen der Autoren, die auf Literaturrecherchen und Diskussionen innerhalb der Fusionsgemeinschaft basieren**". Unsicherheiten wurden durch Szenarien, Wahrscheinlichkeits- und Fuzzy-Modellierung berücksichtigt. * **Tatsächliche Erfahrungswerte (Historische F&E-Kosten):** * Gesamtausgaben für Fusionsforschung in OECD-Ländern (1974-1998): **ca. 30 Mrd. €** [16, unter Berufung auf Grunwald et al., 2003]. * Jährliche Investitionen in die zivile Kernfusionsforschung (2000): **geschätzt 1,4 Mrd. €**. * US-Kongressfinanzierung für Magnetfusions-F&E (1951-1973): **2,5 Mrd. US$** (in US$2000) [16, unter Berufung auf Rowberg, 1999]. * Gesamte öffentliche OECD-Finanzierung der zivilen Fusions-F&E (bis heute): **nicht mehr als 50 Mrd. €** in aktuellen Preisen. * **Schätzungen/Prognosen (Zukünftige Kosten und Marktparameter):** * **Zukünftige F&E-Kosten:** * ITER-Budget: **ca. 10 Mrd. €** (4,6 Mrd. € für Bau, 4,8 Mrd. € für Betrieb) [17, unter Berufung auf Fiore, 2006]. * IFMIF-Kosten: **ca. 600 Mio. €**. * DEMO-Investitionskosten: **ca. 8 Mrd. €** [17, unter Berufung auf Grunwald et al., 2003]. * Gesamte öffentliche Investitionen in Fusions-F&E bis 2050: **60-100 Mrd. €**. * Jährliche F&E-Kosten während der Bereitstellungsphase (ab 2051): **1,2-2,0 Mrd. €** pro Jahr (2051), linear sinkend auf Null bis 2100 [50, Table 1]. * **Kosten von Fusionskraftwerken (FPPs):** * Annahmen zu den **durchschnittlichen Kosten von FPPs** (spezifische Kapitalkosten, jährliche O&M-Kosten, Fusions-COE) basieren auf **Gnansounou und Bednyagin (2007)** und **Han und Ward (2009)**. Für die Investitionsannuität werden **5% Zinsen, 40 Jahre Lebensdauer und 80% Kapazitätsfaktor** angenommen [56, Table 2]. * Die in Tabelle 2 aufgeführten Kosten sind "indikative gewichtete Durchschnittskosten für den gesamten 50-Jahres-Zeitraum von 2051 bis 2100". * **Marktstrompreise:** * Langfristige Grenzkosten (LRMC) repräsentativer Marginaltechnologien (z.B. fortschrittliche Kohle- und Gaskraftwerke) für den Zeithorizont 2050: abgeleitet aus Berechnungen in **Bednyagin (2010)**, Bereich **45–90 €/MWh**, für die weitere Evaluation auf **50–100 €/MWh** angepasst. * Historische (EEX-Daten 2006–2009) Preisspanne (32–100 €/MWh) wird zur Bestätigung der Plausibilität herangezogen. 3. **Falls externe Quellen für die Modell- und Kostenannahmen verwendet wurden – wurden diese modifiziert? Falls ja, wie?** Ja, externe Quellen wurden modifiziert oder spezifisch interpretiert: * **Marktstrompreise:** Die ursprüngliche LRMC-Spanne von **26–112 €/MWh** (Bednyagin, 2010) wurde durch den Ausschluss extremer Brennstoff- und CO2-Preisannahmen auf **45–90 €/MWh** eingegrenzt. Für die weitere Bewertung wurde dann die Spanne auf **50–100 €/MWh** festgelegt. Frühere Schätzungen der UKAEA-Studie (Ward et al., 2002) von 70–130 €/MWh wurden als zu hoch angesehen. * **Szenarien:** Die drei deterministischen Szenarien "A", "B" und "C" entsprechen "grob" (roughly correspond) früheren Szenarien aus **Gnansounou und Bednyagin (2007)** und der **UKAEA-Studie (Ward et al., 2002)**, aber die numerischen Annahmen (z.B. für F&E-Kosten, Kapazitäten, Stromgestehungskosten) wurden für jedes Szenario spezifisch in der vorliegenden Studie definiert. * **"Accelerated" Strategie:** Im Vergleich zur "Baseline"-Strategie wird angenommen, dass zusätzliche **15 Mrd. € (undiskontiert)** in die "Demo"-Phase investiert werden, was zu einer **5%igen Erhöhung der Erfolgswahrscheinlichkeit** und einer **Verkürzung der Dauer um 5 Jahre** führt. 4. **Wie lautet die Annahme zu Lernraten?** Es wird eine **eher konservative Lernrate von 10%** angenommen ("a rather conservative 10% learning rate"). 5. **Wie wurden die Annahmen zu den Lernraten hergeleitet bzw. von wo stammen diese Annahmen?** Die Studie gibt **keine explizite Herleitung oder spezifische Quelle** für die angenommene 10%ige Lernrate an. Es wird angenommen, dass dies Teil der "Autorenschätzungen basierend auf Literaturrecherchen und Diskussionen innerhalb der Fusionsgemeinschaft" ist. Es wird lediglich festgestellt, dass "Basierend auf den entsprechenden jährlichen Hochlauf-Raten und unter Annahme einer eher konservativen Lernrate von 10% die spezifischen Kosten für Fusionskraftwerke verschiedener Baujahre geschätzt werden können". 6. **Wird offengelegt, ob die Kostenabschätzung auf einem Bottom-up-, Top-down- oder hybriden Ansatz basiert?** Die Studie **legt nicht explizit offen**, ob die Kostenabschätzung auf einem Bottom-up-, Top-down- oder hybriden Ansatz basiert. Sie verwendet jedoch **aggregierte Kostenkennzahlen** (z.B. spezifische Kapitalkosten, O&M-Kosten, COE), die aus anderen Referenzstudien (wie Han und Ward, 2009; Gnansounou und Bednyagin, 2007) abgeleitet oder an diese angelehnt sind. Die in der Studie zitierte Aufschlüsselung der Stromkosten durch Hamacher und Bradshaw (2001) in Kategorien wie "fusion reactor core" und "balance of plant" deutet darauf hin, dass die ursprünglichen Quellen möglicherweise einen Bottom-up-Ansatz verwendet haben, aber die vorliegende Studie selbst nutzt diese Werte als aggregierte Eingaben. 7. **Beruht die Kostenherleitung auf physikalischen und technologischen Werten?** Die Kostenherleitung in dieser Studie **beruht nicht direkt auf der detaillierten Berechnung physikalischer und technologischer Werte**. Stattdessen werden **aggregierte Kostenkennzahlen** verwendet, die aus früheren Studien stammen, welche wiederum physikalische und technologische Werte berücksichtigten. Es wird ausdrücklich erwähnt, dass "Earlier works performed with **PROCESS systems code model (Hender et al., 1996) showed that the cost of fusion electricity depends on several key technical parameters, namely: net electric power, thermodynamic efficiency, availability, normalised plasma pressure and Greenwald normalised plasma density**". Die vorliegende Studie greift also auf die Ergebnisse solcher Modelle zurück, anstatt diese selbst durchzuführen. 8. **Werden Materialkosten und Komponentenkosten separat ausgewiesen?** **Nein, Materialkosten und spezifische Komponentenkosten werden in den bereitgestellten Auszügen nicht separat ausgewiesen.** Die Studie zitiert eine Aufschlüsselung der Stromgestehungskosten (COE) aus Hamacher und Bradshaw (2001) in Anteile wie "capital costs for fusion reactor core (39%)", "balance of plant (23%)" und "costs for the replacement of divertor and blanket during operation (30%)". Dies sind aggregierte Kostenkategorien, aber keine detaillierte Auflistung von Material- oder einzelnen Komponentenkosten. Die **"Specific capital cost (mln h/MW)"** ist eine übergeordnete Größe. 9. **Bezieht sich die Studie auf ein Energiesystem (z. B. Integration, Vergleich mit anderen Technologien) oder ist sie rein bezogen auf die Kosten des Kraftwerks und des Reaktors?** Die Studie **bezieht sich auf ein Energiesystem** und bewertet die Fusionsenergie im Kontext zukünftiger globaler Energiesysteme. * **Integration und Vergleich:** Die Analyse der potenziellen Rolle der Fusionsenergie erfolgt in "future energy systems" und beinhaltet den Vergleich mit "competing technologies". * **Marktstrompreise:** Der zukünftige Marktstrompreis wird als **langfristige Grenzkosten (LRMC) konventioneller Technologien** (fortschrittliche Kohle- und Gaskraftwerke) abgeleitet, mit denen die Fusionsenergie konkurrieren muss. * **Marktanteil:** Der "market share of fusion" ist ein entscheidender Faktor für den erwarteten wirtschaftlichen Nutzen. * **Modellierung der Integration:** Die Bewertung der Fusionskraftwerksstrategien basiert auf der "simulation of multi-regional long term electricity supply scenarios with PLANELEC model". * **"Versicherungswert":** Fusion wird als "effective hedge against increased cost of conventional power generation using fossil fuels" und als "significant 'insurance' value in case of unforeseen events" angesehen. * **Positive Externalitäten:** Die Studie betont die Notwendigkeit, weitere wirtschaftliche und soziale Vorteile wie "nicht-elektrische Anwendungen und technologische Spin-offs", "Technologieexporte", "Reduzierung fossiler Brennstoffimporte", "erhöhte Energiesicherheit" und "verbesserte Umwelt" in die sozioökonomische Bewertung einzubeziehen. 10. **Welche Kostenreduktionspotenziale oder wirtschaftlichen Optimierungsansätze werden thematisiert?** * **Lerneffekte:** Es wird ein **10%iger Lerneffekt** angenommen, der dazu führt, dass die Kosten der FPPs während der anfänglichen Bereitstellungsphase (2050–2070) "deutlich sinken", vom 1st-of-a-kind (FOAK) bis zum 10th-of-a-kind (10th-OAK). * **Manageriale Flexibilität (Real Options):** Der zentrale Ansatz der Studie ist die **Bewertung der managerialen Flexibilität**. Dies ermöglicht es den Managern, auf unsichere Marktbedingungen zu reagieren, z.B. die F&E-Bemühungen zu intensivieren oder die Produktion zu erweitern, wenn die Marktbedingungen günstig sind, oder Projekte bei Misserfolg abzubrechen. * **Beschleunigte Entwicklungsstrategie ("Accelerated" Strategy):** Diese Strategie zielt darauf ab, durch höhere Investitionen in die Demonstrationsphase (z.B. Bau mehrerer DEMOs) die **Erfolgswahrscheinlichkeit zu erhöhen** und die **Time-to-Market zu verkürzen**. Dies führt zu einem höheren strategischen Wert und kann die Programmeinnahmen erheblich steigern, auch wenn initial höhere Kosten anfallen. * **Optimiertes Design:** Die Wahl des "optimum build" zielt auf minimale Kosten ab [Konversationsverlauf]. * **Technologische Reife:** Mit fortschreitender Reife der Technologie von FOAK zu 10th-OAK wird eine Kostenreduktion erwartet [55, Konversationsverlauf]. 11. **Was sind die signifikantesten Kostentreiber und ökonomischen Herausforderungen laut Studie?** * **Signifikanteste Kostentreiber:** * **Kosten der Fusionskraftwerke (FPPs):** Insbesondere die spezifischen Investitions- und O&M-Kosten sind entscheidend für die Stromgestehungskosten. Die Sensitivitätsanalyse zeigt, dass die **erwarteten Einnahmen** (die wiederum von den FPP-Kosten und den Strompreisen abhängen) den Realoptionswert am stärksten treiben. * **F&E- und DEMO-Kosten:** Die direkten öffentlichen Ausgaben für die F&E- und Demonstrationsphasen (ITER, IFMIF, DEMO) sind erhebliche Vorabinvestitionen. * **Diskontierungssatz:** Der gewählte Diskontierungssatz hat einen **erheblichen Einfluss** auf den geschätzten Kapitalwert (NPV) des Programms, da die potenziellen Vorteile der Fusion weit in der Zukunft liegen. * **Ökonomische Herausforderungen:** * **Hohe Unsicherheit:** Dies ist die größte Herausforderung. Sie erstreckt sich über einen sehr langen Zeitraum (>100 Jahre) und umfasst: * **Technologische (epistemische) Unsicherheit:** Das **Performance-Risiko** (Ob das Programm eine praktikable Technologie liefern kann, die Strom zu angemessenen Kosten bereitstellt) und das **Zeitrisiko** (Programmverzögerungen). * **Marktunsicherheit (aleatorisch):** Zukünftige Strompreise, Nachfrage, Marktanteil der Fusion, Kosten konkurrierender Technologien und die politische Gestaltung der Umweltpolitik. * **Ungenauigkeit und Vagheit menschlicher Einschätzungen** sowie **fehlende Informationen** (z.B. private F&E-Ausgaben). * **Lange Vorlaufzeit:** Die "extremely long lead time" der Fusionsentwicklung ist problematisch, da die Kosten früh anfallen, während die Vorteile weit in der Zukunft liegen. * **Geringe Anreize im privaten Sektor:** Aufgrund von "spillover effects" in einem liberalisierten Energiesektor, bei denen Unternehmen die Ergebnisse ihrer F&E-Investitionen nicht vollständig nutzen können, sind private Anreize zur Finanzierung von F&E-Projekten unter dem sozial optimalen Niveau. Dies erfordert eine stärkere öffentliche Finanzierung. | X8: In der Studie von Bednyagin und Gnansounou (2011) wird das potenzielle **wirtschaftliche Potenzial von Fusionskraftwerken (Fusion Power Plants, FPPs)** bewertet, indem ihre projizierten Stromgestehungskosten (COE) mit den erwarteten zukünftigen Kosten **konventioneller Energieerzeugungstechnologien** verglichen werden. ### Ergebnis des Vergleichs Das **primäre Ergebnis** der Studie ist, dass Fusionsenergie unter plausiblen Annahmen **wirtschaftlich wettbewerbsfähig** sein kann und erhebliche netto-ökonomische Vorteile mit sich bringen würde. Der Vergleich erfolgt indirekt, indem die Studienautoren einen **zukünftigen Marktpreis für Strom** ableiten, der durch die **langfristigen Grenzkosten (Long-Run Marginal Cost, LRMC)** konventioneller Technologien bestimmt wird. Fusionskraftwerke müssen in diesem Preissegment konkurrieren, um als attraktiv zu gelten. 1. **Vergleichswerte für andere Technologien:** * Als **marginale Stromerzeugungsoptionen für den Zeithorizont 2050** werden **fortschrittliche Kohle- (IGCC) und Gaskraftwerke (NGCC)** betrachtet. * Die vollen Stromkosten (LRMC) dieser repräsentativen marginalen Technologien werden in einer Spanne von **h26–h112 pro MWh** angegeben. Nach Ausschluss extremer Annahmen (verdoppelte Brennstoff- und sehr niedrige CO2-Preise) wird die LRMC-Spanne auf **h45–h90 pro MWh** eingegrenzt. Diese Spanne wird als Basis für die weitere Bewertung gewählt. 2. **Projizierte Fusions-COE (Table 2):** * **Pessimistisches Szenario "A"**: Die Fusions-COE liegt bei **55 h/MWh**. Dieser Wert liegt innerhalb der LRMC-Spanne der konventionellen Technologien (h45–h90 pro MWh). Im Rahmen des deterministischen Szenarios "A" bleibt der Nettokapitalwert (NPV) des Fusions-F&E-Programms negativ, was bedeutet, dass die Einnahmen die Kosten der vorausgehenden F&E-Aktivitäten nicht decken. * **Intermediäres Szenario "B"**: Die Fusions-COE liegt bei **43 h/MWh**. Dieser Wert liegt knapp unterhalb der unteren Grenze der relevanten LRMC-Spanne (h45–h90 pro MWh), was auf eine gute Wettbewerbsfähigkeit hindeutet. Dieses Szenario zeigt einen **erheblich positiven Nettokapitalwert** von 95 Milliarden h für das Fusions-F&E-Programm. * **Optimistisches Szenario "C"**: Die Fusions-COE liegt bei **34 h/MWh**. Dieser Wert liegt deutlich unterhalb der gesamten LRMC-Spanne der konventionellen Technologien (h45–h90 pro MWh), was auf eine **sehr hohe Wettbewerbsfähigkeit** schließen lässt. Dieses Szenario zeigt einen **noch höheren positiven Nettokapitalwert** von 559 Milliarden h. Die Studie schließt daraus, dass die Entwicklung und der Einsatz der Fusionstechnologie unter vernünftigen Annahmen erhebliche netto-ökonomische Vorteile mit sich bringen kann, da sie eine neuartige, umweltfreundliche und **wirtschaftlich wettbewerbsfähige Stromversorgungsoption** darstellt. ### Vergleich mit historischen Werten oder zukunftsgerichteten Projektionen Der Vergleich erfolgt primär mit **zukunftsgerichteten Projektionen** der Kosten für konventionelle Energieerzeugungen. * Die angenommenen Kosten für konventionelle Technologien wie **fortschrittliche Kohle- und Gaskraftwerke** sind **Projektionen für den Zeithorizont 2050**. Diese basieren auf Berechnungen von Bednyagin (2010), die **Sensitivitätsanalysen für verschiedene Brennstoff- und CO2-Preise** umfassen, was eine zukunftsgerichtete Perspektive impliziert. * Zusätzlich werden andere **projizierte Großhandelspreise für Strom**, die in der UKAEA-Studie von Ward et al. (2002) angenommen wurden (h70–130 pro MWh), erwähnt. Allerdings werden auch **historische Werte** herangezogen, um die Plausibilität der projizierten Marktpreise zu prüfen und zu kontextualisieren, nicht aber als primäre Vergleichsgrundlage für zukünftige Fusionskraftwerke: * Es wird festgestellt, dass die abgeleitete LRMC-Spanne von h45–h90 pro MWh **gut mit den tatsächlichen durchschnittlichen monatlichen Preisen für Grundlaststrom übereinstimmt, die zwischen 2006 und 2009 auf dem europäischen Strommarkt beobachtet wurden** (h32–100 pro MWh laut EEX-Daten). | Y8: n/a
A9: 11 | B9: n.a. | C9: Magnetic | D9: Tokamak | E9: 1500 | F9: Capital Cost | G9: FOAK | H9: Relative | I9: 7450 | J9: EUR/kW | K9: 2011 | L9: Bednyagin & Gnansounou (2011) | O9: Scenario B; " rather conservative 10% learning rate"; 2-4% interest rate; 40 years litetime; in 2050; 10 years construction time | P9: CF: 0.8 | Q9: Steady-State | R9: - | S9: - | T9: -
A10: 12 | B10: n.a. | C10: Magnetic | D10: Tokamak | E10: 1500 | F10: Capital Cost | G10: 10th-OAK | H10: Relative | I10: 4300 | J10: EUR/kW | K10: 2011 | L10: Bednyagin & Gnansounou (2011) | O10: Pessimistic scenario A; " rather conservative 10% learning rate"; 5-7% interest rate; 40 years lifetime; in 2070; 10 years construction time | P10: CF: 0.8 | Q10: Steady-State | R10: - | S10: - | T10: -
A11: 13 | B11: n.a. | C11: Magnetic | D11: Tokamak | E11: 1500 | F11: Capital Cost | G11: 10th-OAK | H11: Relative | I11: 3700 | J11: EUR/kW | K11: 2011 | L11: Bednyagin & Gnansounou (2011) | O11: Scenario B; " rather conservative 10% learning rate"; 5-7% interest rate; 40 years lifetime; in 2070; 10 years construction time | P11: CF: 0.8 | Q11: Steady-State | R11: - | S11: - | T11: -
A12: 14 | B12: n.a. | C12: Magnetic | D12: Tokamak | E12: 1500 | F12: Capital Cost | G12: FOAK | H12: Relative | I12: 6000 | J12: EUR/kW | K12: 2011 | L12: Bednyagin & Gnansounou (2011) | O12: Optimistic scenario C; " rather conservative 10% learning rate"; 2-4% interest rate; 40 years litetim; in 2050; 10 years construction time | P12: CF: 0.8 | Q12: Steady-State | R12: - | S12: - | T12: -
A13: 15 | B13: n.a. | C13: Magnetic | D13: Tokamak | E13: 1500 | F13: Capital Cost | G13: 10th-OAK | H13: Relative | I13: 2600 | J13: EUR/kW | K13: 2011 | L13: Bednyagin & Gnansounou (2011) | O13: Optimistic scenario C; " rather conservative 10% learning rate"; 5-7% interest rate; 40 years lifetime; in 2070; 10 years construction time | P13: CF: 0.8 | Q13: Steady-State | R13: - | S13: - | T13: -
A14: 178 | B14: PPCS-C | C14: Magnetic | D14: Tokamak | E14: 1449 | F14: Capital Cost | G14: 10th-OAK | H14: Relative | I14: 4400 | J14: EUR/kW | K14: 2005 | L14: Ward / in Maisonnier et al. (2005) | O14: 6% discount rate; 40 years lifetime; Abgelesen; Fusion power: 3.41 GW; 10th of a kind plant with a corresponding cost reduction factor of 0.65 for fusion specific items; based on conventional superconducting technology, Nb3Sn for the toroidal field and NbTi for the poloidal field. Advances in superconductors, to lower cost materials and to high temperature superconductors are expected to reduce these costs but this is an uncertain issue.; Divertor every 2 years; Blanket every 5 years replacement | P14: 0.75 | Q14: Steady-State with possibility for load-following by decrasing el. Output up to 50% ("Both from the plasma physics and technology viewpoints, it would be feasible to reduce the electrical output by about fifty percent.") | R14: - | S14: - | T14: -
A15: 179 | B15: PPCS-D | C15: Magnetic | D15: Tokamak | E15: 1527 | F15: Capital Cost | G15: 10th-OAK | H15: Relative | I15: 3100 | J15: EUR/kW | K15: 2005 | L15: Ward / in Maisonnier et al. (2005) | O15: 6% discount rate; 40 years lifetime; Abgelesen; Fusion power: 2.53 GW; 10th of a kind plant with a corresponding cost reduction factor of 0.65 for fusion specific items; It is assumed that the advances in superconducting technology are such as to allow the same magnetic field strength to be achieved but with magnets that are half the cost of today's technology; Divertor every 2 years; Blanket every 5 years replacement | P15: 0.75 | Q15: Steady-State with possibility for load-following by decrasing el. Output up to 50% ("Both from the plasma physics and technology viewpoints, it would be feasible to reduce the electrical output by about fifty percent.") | R15: - | S15: - | T15: - | AF15: • Argues for commercializing Laser Inertial Fusion Energy (LIFE) by ~2030. • Uses system modeling to show benefits: reduced CO₂, nuclear waste, plutonium. • Assesses economic competitiveness of LIFE vs. other low-carbon sources. • Proposes a commercialization path with a demo plant operational 10–15 years after ignition proof. Key findings? • Need for new power generation since most U.S. power plants to retire by 2060; 400–900 GW replacements needed; Low-carbon baseload capacity is critical. • Benefits of early commercialization: o CO₂ avoidance: -> Start in 2030 avoids 100–140 Gt CO₂ by 2100; 2040 start reduces this by ~30–35%. -> Present value of CO₂ avoided: $300–600 billion (at $100/t CO₂, 5% discount rate). o Nuclear waste reduction and Plutonium reduction • LIFE commercialization approach: o Developed at Lawrence Livermore National Lab. o Builds on NIF science/tech with changes for plant-scale operation: -> Modular lasers, diode pumping, mass-produced targets, heat management. o Path includes three “Point Designs”: -> LIFE.1: Demo plant (400 MW fusion), existing materials, operational ~10–15 years after ignition. -> LIFE.2: 1 GWe commercial plant with advanced materials. -> LIFE.3: Mature plant with further improvements. o LIFE.1 serves as testbed for qualifying materials/processes in continuous fusion. o Natural scaling benefit: larger plants yield better laser-to-electric efficiency. • COE is competitive with other low-carbon baseload and cheaper than fossil fuel if CO₂ cost is $50–100/ton. o Key cost drivers: chamber material (ODS steel), target cost, target gain. • Aim: deploy first commercial LIFE plant in the early 2030s or sooner. -> Paper Conclusion: • LIFE presents a compelling case for accelerated fusion development. • A demo plant should be designed/built within 10–15 years after ignition proof. • Design minimizes R&D needs by using existing materials/processes. • Once operational, the system enables material/process qualification for commercial plants. • Despite its pre-conceptual stage, LIFE is economically competitive. • A pilot plant is feasible in 10–15 years with integrated R&D and construction. • The path is ambitious and carries technical risk, requiring a national effort across industry, labs, government, and academia. • The study calls for immediate action and hopes to inspire renewed commitment to fusion demonstration and deployment. | AG15: **Worüber handelt die Studie?** Die Studie, mit dem Titel **"LIFE: The Case for Early Commercialization of Fusion Energy"**, stellt den Fall für die frühe Kommerzialisierung von Laser-Trägheitsfusionsenergie (LIFE) dar. Sie quantifiziert die Vorteile der Fusionsenergie in Bezug auf die Vermeidung von Kohlenstoffemissionen, Nuklearabfällen und Plutoniumproduktion durch Systemmodellierungen des US-amerikanischen Stromerzeugungssystems. Die Studie analysiert auch die Sensitivität der erzielten Vorteile in Bezug auf den Zeitpunkt des Markteintritts und zeigt die Bedeutung eines Markteintritts im Zeitraum um 2030 auf. Darüber hinaus werden wirtschaftliche Modellierungsergebnisse präsentiert, die zeigen, dass Fusionsenergie mit anderen kohlenstoffarmen Energiequellen wettbewerbsfähig sein kann. Die Arbeit beschreibt auch den Kommerzialisierungspfad für LIFE, einschließlich des Vorschlags zum Bau einer Demonstrationsanlage, die innerhalb von 10 bis 15 Jahren zu einem kontinuierlichen Fusionsbetrieb fähig ist, um die Prozesse und Materialien für ein kommerzielles Fusionskraftwerk zu qualifizieren. **Welche Kernaussagen werden in der Studie genannt?** * **Bedarf an neuer Stromerzeugung:** Die Welt befindet sich in einer transformatorischen Phase der Stromerzeugung und -nutzung. In den USA wird bis 2060 praktisch die gesamte bestehende Kraftwerksflotte stillgelegt, und bis 2100 müssen etwa 900 neue GW-Klasse-Kraftwerke gebaut werden, selbst ohne Nachfragesteigerung sind es über 400 GW. Ein erheblicher Teil dieses Ersatzbedarfs muss durch kohlenstoffarme Grundlast-Energieerzeugung gedeckt werden. * **Vorteile der frühen Kommerzialisierung:** * **CO2-Vermeidung:** Wenn der erste kommerzielle Fusionsbetrieb im Jahr 2030 beginnt, können zwischen 100 und 140 Gigatonnen (GT) CO2 bis 2100 vermieden werden. Bei einem Markteintritt im Jahr 2040 verringert sich die CO2-Vermeidung um 30% bis 35% im Vergleich zu 2030. Der Barwert der vermiedenen Kohlenstoffemissionen liegt zwischen 300 und 600 Milliarden US-Dollar (bei 5% Abzinsung und $100/MT CO2). * **Nuklearabfall-Vermeidung:** Bei einem Betriebsstart im Jahr 2030 können 230.000 bis 360.000 metrische Tonnen hochradioaktiver Nuklearabfälle vermieden werden (entspricht 3,0 bis 4,5 zusätzlichen "Yucca-Mountain-Äquivalenten"). Eine Verzögerung auf 2040 würde die Abfallvermeidung um 85.000 bis 110.000 metrische Tonnen reduzieren. * **Plutonium-Vermeidung:** Wenn die Fusionskraftwerke schnelle Reaktoren mit Wiederaufarbeitung ersetzen, können im Jahr 2100 zwischen 3000 und 4000 metrische Tonnen gelagerten Plutoniums vermieden werden, wenn der erste kommerzielle Betrieb 2030 beginnt. Ein Start im Jahr 2040 statt 2030 würde die Menge an gelagertem Plutonium bis 2100 um über 800.000 kg erhöhen, was die Proliferationsbedenken stark reduziert. * **Marktmöglichkeiten:** Es besteht eine starke Motivation, die Fusionsenergie rechtzeitig zu kommerzialisieren, um an der Rekapitalisierung des Stromnetzes in den kommenden Jahrzehnten teilzuhaben, da die Marktchancen danach begrenzt wären. * **Der LIFE-Ansatz zur Kommerzialisierung:** * Der LIFE-Ansatz wird am Lawrence Livermore National Laboratory in Partnerschaft mit anderen Einrichtungen entwickelt. * Er nutzt die Wissenschaft und Technologie der National Ignition Facility (NIF), einschließlich der Lasertechnologie und der Targetphysik, mit Anpassungen für den Kraftwerksbetrieb (kompaktere, modulare Laserarchitektur, aktives Wärmemanagement, Diodenpumpen für Effizienz und massenproduzierbare Fusionstargets). * Der Kommerzialisierungspfad umfasst drei Entwurfspunkte (Point Designs): LIFE.1 (Demonstrationsanlage, 400 MW Fusionsleistung, Einsatz bestehender Materialien, voraussichtlich 10-15 Jahre nach NIF-Zündung betriebsbereit), LIFE.2 (1 GWe kommerzielles Kraftwerk, fortschrittliche Materialien) und LIFE.3 (ausgereifte Technologie mit potenziellen Verbesserungen). * **LIFE.1 dient als Teststand** zur Demonstration der benötigten Betriebsabläufe und zur Qualifizierung von Materialien und Prozessen in einer kontinuierlichen Fusionsumgebung. * Es besteht ein **natürlicher Skaleneffekt** für LIFE, da die Effizienz der Umwandlung von Laserenergie in Fusionsenergie mit der Skalierung der Anlage zu höherer elektrischer Leistung steigt. * **Wirtschaftlichkeit:** * Die geschätzten Investitionskosten für alle drei LIFE-Systeme liegen zwischen 4 und 6 Milliarden US-Dollar. * Die **Stromgestehungskosten (Cost of Electricity, COE)** für LIFE sind vergleichbar mit anderen kohlenstoffarmen Grundlast-Energiequellen und liegen unter den Kosten der fossilen Brennstofferzeugung, wenn die Kohlenstoffkosten 50 bis 100 US-Dollar pro Tonne überschreiten. * Die **wichtigsten wirtschaftlichen Parameter** sind das Strukturmaterial der Fusionskammer (oxiddispersionsverstärkter Stahl), die Fusionszielkosten und die Zieleffizienz. **Was ist das Ziel der Studie?** Das primäre Ziel der Studie ist es, **den Fall für die frühe Kommerzialisierung von Laser-Trägheitsfusionsenergie (LIFE) darzulegen**. Sie zielt darauf ab, die Vorteile einer Fusionsenergieoption in einem relevanten Zeitrahmen, der die Kapazitätslücke füllen kann, zu bewerten und einen Weg zur Erreichung dieses Ziels mithilfe von LIFE aufzuzeigen. Letztendlich ist es das Ziel, die Entwicklung der Fusionsenergie zu beschleunigen und das Ziel zu setzen, den ersten kommerziellen Betrieb in den 2030er Jahren oder früher zu erreichen. **Was ist das Fazit der Studie?** Die Studie kommt zu dem Schluss, dass die **Bewertung der LIFE-Technologie einen überzeugenden Grund liefert, die Entwicklung der Fusionsenergie zu beschleunigen** und sich das Ziel zu setzen, den ersten kommerziellen Betrieb in den 2030er Jahren oder früher zu erreichen. Der vorgeschlagene Ansatz zur Erreichung dieses Ziels ist es, die auf der NIF demonstrierte Wissenschaft und Technologie zu nutzen und innerhalb von zehn bis fünfzehn Jahren nach der NIF-Zündung eine Demonstrationsanlage für Fusionskraft zu entwerfen und zu bauen. Das Design der Demonstrationsanlage maximiert die Nutzung bestehender Materialien und Prozesse, um den Forschungs- und Entwicklungsbedarf zu minimieren. Sobald ein kontinuierliches Fusionssystem in Betrieb ist, ermöglicht dies die Qualifizierung von Materialien und Prozessen, die für die kommerzielle Fusionsenergie erforderlich sind. Obwohl die ökonomische Bewertung von LIFE auf einem vorkonzeptionellen Niveau basiert, zeigt sie, dass die **Wirtschaftlichkeit von LIFE gut mit anderen kohlenstoffarmen Technologien vergleichbar ist**. Ein Design- und Bauplan zeigt, dass der erste Pilotanlagenbetrieb 10 bis 15 Jahre nach Projektbeginn möglich ist, abhängig von der Integration der unterstützenden F&E-Aktivitäten mit den Design- und Bauplänen. Die Studie erkennt an, dass dieser Ansatz zur Kommerzialisierung der Fusionsenergie **technische Risiken birgt und aggressiv ist**, und betont, dass ein nationales Engagement von Industrie, Laboren, Akademikern, Regierung und internationalen Partnern erforderlich ist. Das Fazit unterstreicht die **Dringlichkeit des Bedarfs und die überzeugenden Vorteile** und hofft, dass diese Studie andere Interessengruppen motivieren wird, die Fusionsenergieoption neu zu bewerten und die notwendigen nächsten Schritte in Richtung Konzeptstudien und Technologiedemonstrationen zu unternehmen. | AH15: Gerne, hier ist eine Schritt-für-Schritt-Übersicht darüber, was in der Studie "LIFE: The Case for Early Commercialization of Fusion Energy" gemacht und wie vorgegangen wurde: Die Studie von Anklam et al. (2011) bewertet die Vorteile einer **frühen Kommerzialisierung der Fusionsenergie**, insbesondere der Laser Inertial Fusion Energy (LIFE), und skizziert einen Weg dorthin. ### 1. Ausgangslage und Problembeschreibung * **Identifikation des globalen Energiebedarfs**: Die Studie stellt fest, dass die Welt vor einer transformativen Phase in der Stromerzeugung steht. Entwicklungsländer benötigen drastisch mehr Strom, während in entwickelten Ländern wie den USA, Japan und Europa veraltete Kraftwerke in den kommenden Jahrzehnten ersetzt werden müssen. * **Kapazitätslücke in den USA**: Für die USA wird ein Szenario skizziert, in dem sich der Strombedarf bis zum Jahrhundertende ungefähr verdoppelt und die gesamte bestehende Kraftwerksflotte bis 2060 stillgelegt sein wird. Dies erfordert den Bau von etwa 900 neuen GW-Klasse-Kraftwerken bis 2100, selbst ohne Nachfragesteigerung sind es noch über 400 GW. * **Anforderung an die neue Kapazität**: Ein erheblicher Teil dieses Ersatzbedarfs muss durch **kohlenstoffarme Grundlast-Stromerzeugung** gedeckt werden. * **Ziel der Studie**: Die Studie bewertet die Vorteile einer Fusionsenergieoption in einem relevanten Zeitrahmen, um diese Kapazitätslücke zu füllen, und skizziert einen Weg dazu mit Laser Inertial Fusion Energy (LIFE). ### 2. Quantifizierung der Vorteile der frühen Kommerzialisierung der Fusionsenergie Es wurden **Systemmodellierungen des US-Stromerzeugungssystems** durchgeführt, um die Vorteile der Fusionsenergie zu quantifizieren. * **Vermeidung von CO2-Emissionen**: * **Szenarioannahme**: Es wurde angenommen, dass jedes gebaute Fusionskraftwerk ein Kohlekraftwerk ersetzt. Die Wachstumsrate der Fusions-Marktdurchdringung wurde durch die Nachfrage (gemäß Abb. 1) und den Aufbau der Lieferkette (Verdopplung der Baukapazität alle 5 oder 10 Jahre) begrenzt. * **Ergebnisse**: Bei einem Kommerzstarts im Jahr 2030 könnten kumulativ zwischen **100 und 140 Gigatonnen (GT) CO2** bis 2100 vermieden werden. Ein Start 2040 würde zu 30-35 % weniger CO2-Vermeidung führen. * **Kostenbewertung**: Bei angenommenen CO2-Kosten von 100 $/MT (Millionen Tonnen) würde der Barwert des vermiedenen Kohlenstoffs zwischen 300 und 600 Milliarden US-Dollar (mit einem Diskontsatz von 5 %) liegen. * **Erweiterung des Szenarios**: Falls LIFE Kohlekraftwerke mit Kohlenstoffabscheidung und -speicherung (CCS) ersetzen würde, wäre der vermiedene Wert noch größer, da CCS die thermische Effizienz reduziert. * **Vermeidung von nuklearem Abfall und Plutoniumproduktion**: * **Szenarioannahme für Abfall**: Wenn LIFE neue Leichtwasserreaktoren mit einmaligem Brennstoffkreislauf ersetzen würde, wäre die Metrik die **Vermeidung von hochradioaktivem Atommüll**. * **Ergebnisse für Abfall**: Ein kommerzieller Start 2030 könnte die Vermeidung von 230.000 bis 360.000 Tonnen hochradioaktiven Atommülls bedeuten (entspricht 3,0 bis 4,5 zusätzlichen "Yucca-Mountain-Äquivalenten"). Ein Start 2040 würde die Abfallvermeidung um 85.000 bis 110.000 Tonnen reduzieren. * **Szenarioannahme für Plutonium**: Wenn LIFE stattdessen schnelle Reaktoren mit Wiederaufbereitung ersetzen würde, wäre die Metrik die **Vermeidung von Plutonium in der Lagerung**. * **Ergebnisse für Plutonium**: Ein kommerzieller Start 2030 könnte die Vermeidung von 3000 bis 4000 Tonnen gelagertem Plutonium bedeuten. Ein Start 2040 würde die Plutoniummenge im Jahr 2100 um über 800.000 kg (100.000 signifikante Mengen) erhöhen. Dies unterstreicht die Bedeutung eines frühen Starts für die **Reduzierung von Proliferationsrisiken**. * **Wichtigkeit des Zeitpunkts**: Die Studie betont, dass die frühen 2030er-Jahre von entscheidender Bedeutung sind, da der Stromnetzpark in den nächsten Jahrzehnten rekapitalisiert wird. Nach Abschluss der Rekapitalisierung sind die Marktchancen für die Erfüllung des Bedarfs begrenzt, was die Vorteile der Fusionsenergie erheblich mindern würde. ### 3. Der LIFE-Ansatz zur Kommerzialisierung Der LIFE-Ansatz wird vom Lawrence Livermore National Laboratory (LLNL) in Partnerschaft mit anderen Einrichtungen entwickelt. * **Grundlagen**: Das Konzept nutzt die Wissenschaft und Technologie, die im National Ignition Facility (NIF) demonstriert wird, einschließlich der gleichen grundlegenden Lasertechnologie und Zielphysik (Neodym-dotierte Glas-Gain-Medien, indirekt angetriebene Hot-Spot-Zündung). * **Anpassungen für den Kraftwerksbetrieb**: Das Design wird jedoch angepasst für: * Eine **kompaktere, modulare Laserarchitektur** für hohe Verfügbarkeit im Kraftwerksbetrieb. * **Aktives Wärmemanagement** für höhere Wiederholungsraten (10 bis 20 Hz). * **Diodenpumpen anstelle von Blitzlampen** für Kraftwerks-Lasereffizienz (10-20 %). * **Massenproduzierbare Fusionstargets**. * **Drei Designpunkte für die Kommerzialisierung** (Table I): * **LIFE.1**: * **Zweck**: Ein Demonstrationseinrichtung, die 400 MW Fusionsleistung erzeugt. Sie soll als **Testbett für kommerzielle Kraftwerksprozesse und zur Qualifizierung von Materialien und Prozessen** in einer kontinuierlichen Fusionsumgebung dienen. * **Technologie**: Maximiert die Nutzung bestehender Materialien und Technologien und soll 10-15 Jahre nach der Zündung auf NIF betriebsbereit sein. Es wird ein beschleunigtes Testschema für Materialien verwendet. * **LIFE.2**: * **Zweck**: Ein 1 GWe kommerzielles Kraftwerk, möglicherweise eine Hochrüstung von LIFE.1. * **Technologie**: Nutzt die gleiche Lasertechnologie wie LIFE.1, aber fortschrittlichere, strahlenresistente Strukturmaterialien (Oxid-Dispersions-gehärteter Stahl, ODS) für höhere Temperaturen und Leistungsdichten. Diese Materialien sollen auf LIFE.1 qualifiziert werden. * **LIFE.3**: * **Zweck**: Zeigt das Potenzial für die Wirtschaftlichkeit einer ausgereiften LIFE-Technologie auf. * **Technologie**: Basiert auf erwarteten Verbesserungen bei der Targeteffizienz, niedrigeren Fusions-Target-Kosten und höheren Betriebstemperaturen. * **Skaleneffekte**: LIFE weist eine natürliche Skalenökonomie auf, da die Effizienz der Umwandlung von Laserenergie in Fusionsenergie mit der Skalierung zu größerer elektrischer Leistung zunimmt. Größere Anlagen reduzieren die Kapitalintensität ($/kW). ### 4. Wirtschaftlichkeitsanalyse (LIFE Economics) Um die Wettbewerbsfähigkeit von LIFE zu bewerten, wurden präkonzeptionelle Schätzungen der Kapitalkosten und Stromgestehungskosten (Cost of Electricity, COE) entwickelt. * **Kostenkategorisierung**: Die LIFE-Anlage ist in etwa 50 Kostenstellen unterteilt. * **Schätzung der Laser-Systemkosten**: Diese wurden mittels einer **Bottom-up-Methodik** geschätzt, wobei die Einheitskosten aus Lieferantenangeboten und NIF-Projektdaten abgeleitet wurden. Es wurden **Kostensenkungen aufgrund von Fertigungslernkurven** berücksichtigt. * **Schätzung weiterer Systemkosten**: Kosten für Fusionsantrieb, Tritiumanlage und Stromwandlungssysteme wurden aus der Literatur übernommen und mittels Standard-Skalierungsbeziehungen an den LIFE-Betriebspunkt angepasst. * **Fusions-Target-Kosten**: Die Einheitskosten der Fusionstargets wurden aus einer Target-Fertigungsstudie abgeleitet. * **Betriebs- und Wartungskosten (O&M)**: Jährliche Nicht-Brennstoff-Betriebs-, Wartungs- und inkrementelle Kapitalkosten wurden als Prozentsätze der gesamten Anlagenkapitalkosten angenommen, abgeleitet aus der MIT-Publikation "The Future of Nuclear Power" (2009). * **Indirekte Kosten**: Multiplikatoren für indirekte Kosten stammen aus den Gen IV-Kostenabschätzung-Richtlinien, und Differenzen bei Kapital- und indirekten Kosten zwischen nuklearen und konventionellen Systemen wurden aus einer General Atomic-Studie übernommen. * **Anlagenverfügbarkeit**: Für ein "Zehntes-Anlagen"-Modell wurde eine hohe Verfügbarkeit von 92 % angenommen, ermöglicht durch die modulare Architektur des Anlagendesigns. * **Berechnung der Stromgestehungskosten (COE)**: Die COE wurden mithilfe der **Discounted-Cashflow-Methode** berechnet, die ebenfalls im MIT-Bericht von 2009 beschrieben ist. * **Kosten für alternative Technologien**: Die Kosten für alternative Stromerzeugungstechnologien wurden aus einer neueren Arbeit von Nicholson (2010) abgeleitet. * **Ergebnisse und Vergleich**: Die drei LIFE-Systeme (LIFE.1, LIFE.2, LIFE.3) haben geschätzte Kapitalkosten im Bereich von **4 bis 6 Milliarden US-Dollar**. Die geschätzten COE für LIFE (21,5 bis 36,4 Mills/kWh in 1999 US-Dollar, abgeleitet aus Fig. 4) sind **vergleichbar mit anderen kohlenstoffarmen Grundlast-Energiequellen** und niedriger als die Kosten der fossilen Brennstofferzeugung, wenn die Kohlenstoffkosten 50 bis 100 $/MT übersteigen. * **Sensitivitätsanalyse (Monte Carlo)**: Eine Sensitivitätsanalyse der COE zeigte, dass die am stärksten beeinflussenden wirtschaftlichen Parameter das **Strukturmaterial der Fusionskammer**, die **Fusions-Target-Kosten** und die **Target-Effizienz** sind. Dies unterstreicht die Bedeutung der Materialentwicklung (wie ODS-Stahl) und der Target-Entwicklung. ### 5. Kommerzialisierungszeitplan * **Indikativer Zeitplan**: Ein Zeitplan wird vorgeschlagen, der den Beginn des **ersten Pilotbetriebs etwa 12 Jahre nach Projektstart** vorsieht. * **Grundlagen für den Zeitplan**: Die Dauer für Design und Bau orientiert sich an Erfahrungen aus dem Bau des NIF und anderen Großprojekten. * **Integration von Forschung und Entwicklung (R&D)**: Der Zeitplan muss vollständig mit den unterstützenden F&E-Aktivitäten integriert werden. * **Phase 1 (Anfangs-F&E)**: Zielt auf die **Machbarkeitsdemonstration** der einzelnen Technologien ab, um die Grundlage für die Vorplanung der Pilotanlage zu schaffen. * **Phase 2 (Erweiterte F&E)**: Übergang zu Tests von Anlagenkomponenten in Originalgröße, um den Bau und die Beschaffung von Anlagenteilen vorzubereiten. * **Technische Risikoreduzierung**: Beispiele für Aktivitäten zur Risikoreduzierung sind die Massenproduktion von Fusionstargets, die Entwicklung von Hochleistungs-Laserkomponenten und Fusions-Engine-Strukturmaterialien. ### 6. Schlussfolgerungen * **Dringlichkeit und Vorteile**: Die Studie kommt zu dem Schluss, dass ein zwingender Grund besteht, die Entwicklung der Fusionstechnologie zu beschleunigen und das Ziel zu setzen, den ersten kommerziellen Betrieb in den **2030er Jahren oder früher** zu erreichen. Die Notwendigkeit ist dringend, und die Vorteile sind überzeugend. * **Vorgeschlagener Ansatz**: Der Ansatz besteht darin, die auf NIF demonstrierte Wissenschaft und Technologie zu nutzen und innerhalb von 10 bis 15 Jahren nach NIF-Zündung ein Fusionskraftwerk-Demonstrationsanlage zu entwerfen und zu bauen. * **Wirtschaftliches Potenzial**: Eine präkonzeptionelle Bewertung der LIFE-Wirtschaftlichkeit zeigt, dass sie sich gut mit anderen kohlenstoffarmen Technologien vergleicht. * **Herausforderungen**: Dieser Kommerzialisierungsansatz birgt technische Risiken und ist ambitioniert. Er erfordert ein **nationales Engagement** und ein Team aus Industrie, nationalen Laboren, Wissenschaft, Regierung, Regulierungsbehörden und internationalen Partnern. * **Nächste Schritte**: Die nächsten Schritte sind die Durchführung konzeptioneller Designstudien und der Technologiedemonstrationen, die erforderlich sind, um die Fusionskommerzialisierung mit der gebotenen Konzentration und Dringlichkeit voranzutreiben. | AI15: Main cost drivers and economic challenges: • Chamber structural material is the most critical cost driver. → Emphasizes need for advanced materials like oxide dispersion-strengthened (ODS) steel for high temperatures and radiation resistance. • Target cost and efficiency are the next key economic levers. → Improvements in target manufacturing and gain are crucial for overall economics. • Cost estimate uncertainty due to pre-conceptual design stage. → More detailed engineering is required; uncertainty is inherent in early-stage development. • Importance of early market entry: → Delaying commercialization (e.g., 2040 vs. 2030) significantly reduces: o Avoided CO₂ emissions o Avoided nuclear waste o Avoided plutonium accumulation Cost reduction potencials and economic optimization approaches: • Economies of scale: → Laser-to-fusion efficiency improves with plant size, reducing $/kW. → Motivates design of larger plants once investor confidence grows. • Advanced materials (ODS steel): → Enable higher temperatures and power density. → LIFE.1 is designed as a testbed to qualify these materials. • Higher operating temperatures & thermal-electric efficiency: → Efficiency increases from 43% (LIFE.1) to 53% (LIFE.3). • Modular architecture & high availability: → Later plants (LIFE.2, LIFE.3) assume 92% availability. → High availability reduces LCOE by spreading fixed costs over more output. → Lasers are redesigned to be compact, modular, and serviceable. • Diode pumping for laser efficiency instead of flash lamps: → Increases laser efficiency to 10–20%. → Reduces internal power use and operational cost. • Mass production of fusion targets: → Target cost reduction through parallel development and scaling. → validated on NIF • Leverage of existing tech (NIF): → Uses proven NIF laser and target physics. → LIFE.1 maximizes reuse of existing materials to minimize R&D burden. • Material/process qualification under fusion conditions: → LIFE.1 provides continuous fusion environment to qualify and test critical components. • Learning curves in laser manufacturing: → Cost reductions expected as production scales. → Learning rates based on NIF experience. • Competitiveness with low-carbon technologies: → LIFE’s LCOE is comparable to other baseload low-carbon sources. → Becomes cheaper than fossil fuels if carbon costs exceed $50–100/tCO2. • Use of non-nuclear-grade systems where possible: → General Atomics study used to identify where lower-cost conventional systems can substitute costly nuclear components (costly due to regulations), reducing capital and indirect costs. | AJ15: 1. Signifikanteste Kostentreiber und ökonomische Herausforderungen laut Studie: • Fusionskammer-Strukturmaterial: Der kostentreibendste ökonomische Parameter ist das Strukturmaterial der Fusionskammer. Dies unterstreicht die Bedeutung der laufenden Entwicklung von oxiddispersionsgehärteten Stählen (ODS-Stahl), die hohe Betriebstemperaturen und eine ausgezeichnete Strahlenschädigungsresistenz ermöglichen. • Fusions-Targetkosten und Targeteffizienz: Die nächstwichtigsten Hebel für die Wirtschaftlichkeit sind die Kosten der Fusions-Targets und deren Effizienz. • Unsicherheit der Kostenabschätzungen: Die aktuellen Kostenabschätzungen basieren auf einem "pre-conceptual design"-Niveau, was bedeutet, dass noch zusätzliche Arbeit und Detailplanung erforderlich sind. Dies stellt eine inhärente Herausforderung in frühen Entwicklungsphasen dar. • Wichtigkeit des frühen Markteintritts: Es besteht eine starke Motivation, die Kommerzialisierung rechtzeitig abzuschließen, um am Prozess der Rekapitalisierung des Stromnetzes in den nächsten Jahrzehnten teilzuhaben. Ein späterer Markteintritt (z.B. 2040 statt 2030) würde die vermiedenen CO2-Emissionen, die vermiedene Menge an hochradioaktivem Atommüll und die vermiedene Plutoniummenge erheblich reduzieren. Die Kommerzialisierung erfordert einen "aggressiven" Ansatz und birgt "technische Risiken". 2. Kostenreduktionspotenziale oder wirtschaftliche Optimierungsansätze: • Natürliche Skaleneffekte (Economy of Scale): Das LIFE-Konzept weist eine "natürliche Skaleneffizienz" auf. Die Effizienz der Umwandlung von Laserenergie in Fusionsenergie steigt mit zunehmender elektrischer Leistung der Anlage, was zu einer geringeren Kapitalintensität ($/kW) bei größeren Anlagen führt. Dies motiviert den Entwurf größerer Anlagen, sobald Investorenvertrauen gewonnen wurde. • Fortschrittliche Materialien (ODS-Stahl): Die Verwendung von strahlungsresistenten Strukturmaterialien wie oxiddispersionsgehärtetem Stahl (ODS) ermöglicht höhere Betriebstemperaturen und höhere Leistungsdichten. Dies ist entscheidend für die Wirtschaftlichkeit und wird als der wichtigste ökonomische Parameter hervorgehoben. LIFE.1 soll als Testbett zur Qualifizierung dieser Materialien dienen. • Höhere Betriebstemperaturen und thermisch-elektrische Effizienz: Die Weiterentwicklung zu Designs wie LIFE.3 zielt auf höhere Betriebstemperaturen ab, was die thermisch-elektrische Effizienz von 43% (LIFE.1) auf 53% (LIFE.3) steigert. • Modulare Architektur und hohe Verfügbarkeit: Das modulare Design der Anlage ermöglicht eine hohe Verfügbarkeit von 92% für spätere Anlagen (LIFE.2 und LIFE.3). Eine hohe Anlagenverfügbarkeit ist ein direkter Weg zur Reduzierung der Stromgestehungskosten (LCOE), da die Fixkosten über eine größere produzierte Strommenge verteilt werden. Die Lasersysteme werden zudem kompakter und modularer für hohen Verfügbarkeitsbetrieb gestaltet. • Diodenpumpung für Lasereffizienz: Die Verwendung von Dioden statt Blitzlampen für das Pumpen der Laser ermöglicht eine höhere Lasereffizienz von 10% bis 20%, was für den Kraftwerksbetrieb unerlässlich ist. Eine höhere Lasereffizienz reduziert den Eigenstromverbrauch und damit die Betriebskosten. • Massenproduktion von Fusions-Targets: Die Fähigkeit, Fusions-Targets in Massenproduktion herzustellen, ist ein Ziel, das zu niedrigeren Targetkosten führen soll. Die Targetentwicklung kann parallel zu anderen Aktivitäten erfolgen und auf der NIF validiert werden. • Nutzung und Weiterentwicklung bestehender Technologien: Der Kommerzialisierungsansatz nutzt die auf der National Ignition Facility (NIF) demonstrierte Wissenschaft und Technologie. Dies beinhaltet dieselbe grundlegende Lasertechnologie und Targetphysik. LIFE.1 ist darauf ausgelegt, bestehende Materialien und Technologien maximal zu nutzen, um den F&E-Bedarf zu minimieren. • Qualifizierung von Materialien und Prozessen: LIFE.1 wird eine Umgebung bieten, um Materialien und Prozesse unter kontinuierlichem Fusionsbetrieb zu qualifizieren. Dies ist entscheidend für die Entwicklung kommerzieller Fusionskraftwerke. • Kostenreduktionen durch Fertigungslernkurven: Für Laser-Systemkosten werden Kostenreduktionen aufgrund von Fertigungslernkurven erwartet, da viele Komponenten in großen Mengen produziert werden. Die verwendeten Lernraten basieren auf Erfahrungen mit NIF. • Vergleichbare Wirtschaftlichkeit mit anderen kohlenstoffarmen Technologien: Die geschätzten Stromgestehungskosten für LIFE sind vergleichbar mit anderen Grundlast-Energiequellen und niedriger als die Kosten der fossilen Brennstofferzeugung, wenn die CO2-Kosten 50 bis 100 $/MT übersteigen. Dies positioniert LIFE als wettbewerbsfähige Option in einer zukünftigen, kohlenstoffarmen Energielandschaft. • Nutzung von Studien zu Nicht-Nukleargrad-Komponenten: Die "General Atomics study" wurde genutzt, um Kapital- und indirekte Kostenunterschiede zwischen nuklearem und konventionellem Industriestandard für Systeme und Strukturen abzuleiten. Dies deutet auf das Potenzial hin, Kosten zu senken, indem wo möglich nicht-nukleare Komponenten verwendet werden, die weniger strengen (und teureren) Anforderungen unterliegen | AK15: • Plant Breakdown: o The LIFE plant is divided into ~50 cost centers (not further specified). • Laser System Costs: o Estimated using a bottom-up approach but values not further specified. o Unit costs based on vendor quotes and NIF data. o Manufacturing learning curves applied (based on NIF experience), no value given. o Design improvements for power plant use: compact modular lasers, active cooling, diode pumping (10–20% efficiency), high repetition rate (10–20 Hz). • Fusion Core, Tritium Systems & Power Conversion: o Costs adapted from literature (e.g. other ICF reactor designs, Nuclear Energy Cost Data Base etc.) using standard scaling laws to match LIFE specifications, formula not specified. • Fusion Target (Fuel Pellet) Costs: o Unit costs derived from internal target manufacturing study. • O&M and Incremental Capex: o Assumed as fixed percentages of total plant capital cost. o Percentages taken from MIT's 2009 Future of Nuclear Power report. • Indirect Cost Factors: o Based on Gen IV Cost Estimating Guidelines. o Adjustments for nuclear vs. conventional structures taken from a General Atomics study. • Plant Availability: o For a 10th-of-a-kind plant, 92% availability is assumed and enabled by modular system design. • LCOE Calculation: o Uses discounted cash flow (DCF) methodology per MIT 2009 report. • LIFE Point Designs (LIFE.1, LIFE.2, LIFE.3): o LCOE reflects differing maturity levels: -> LIFE.1 (FOAK): Highest cost, testbed using existing materials. -> LIFE.3: Most mature, lowest cost, includes improved target efficiency, cheaper targets, higher operating temps. o Key cost drivers: laser energy, repetition rate, net electric gain, thermal efficiency, first wall lifetime, neutron flux, fusion power. o LCOE also influenced by Carbon costs | AL15: • Aufteilung der Anlage: Die gesamte LIFE-Anlage ist in etwa 50 Kostenstellen (cost centers) unterteilt, die nicht weiter spezifiziert werden. • Lasersystemkosten: o Diese Kosten werden mit einer Bottom-up-Methodik geschätzt. o Die Stückkosten für Laserkomponenten werden aus Anbieterangeboten (vendor quotes) und Daten des NIF-Projekts (National Ignition Facility) abgeleitet. o Es werden Kostensenkungen aufgrund von Fertigungslernkurven (manufacturing learning) geschätzt, wobei die verwendeten Lernraten durch die Erfahrungen mit NIF beeinflusst wurden. o Die Lasersysteme von LIFE nutzen die gleiche grundlegende Lasertechnologie wie NIF, aber die Designs wurden für den Kraftwerksbetrieb modifiziert. Dazu gehören eine kompaktere, modulare Architektur, aktives Wärmemanagement für höhere Wiederholungsraten (10 bis 20 Hz) und Diodenpumpen für höhere Effizienz (~10% bis 20%). • Kosten für Fusions-"Triebwerk", Tritium-Anlage und Energieumwandlungssysteme: o Diese Kosten werden aus bestehenden Studien in der Literatur entnommen und mittels Standard-Skalierungsbeziehungen an den LIFE-Betriebspunkt angepasst. • Kosten für Fusions-Targets (Brennstoffpellets): o Die Stückkosten für die Targets werden aus einer spezifischen internen Target-Herstellungsstudie abgeleitet. • Betriebs- und Wartungskosten (O&M-Kosten) und inkrementelle Kapitalkosten: o Es wird angenommen, dass diese jährlichen Kosten als Prozentsätze der gesamten Kapitalkosten der Anlage skalieren. o Die verwendeten Prozentsätze wurden aus der 2009er MIT-Publikation "The Future of Nuclear Power" abgeleitet. • Indirekte Kostenfaktoren: o Diese stammen aus den "Gen IV cost estimating guidelines". o Kostenunterschiede zwischen nuklearen und konventionellen Systemen und Strukturen wurden aus einer General Atomic Studie übernommen. • Anlagenverfügbarkeit: o Für eine "10th of a kind plant" (also eine weiter entwickelte Anlage nach den ersten Prototypen) wird eine hohe Verfügbarkeit von 92% angenommen. Diese hohe Verfügbarkeit wird durch die modulare Architektur der Anlage ermöglicht. • Berechnung der Stromgestehungskosten (LCOE): o Die Berechnung erfolgt mithilfe der Diskontierter-Cashflow-Methode (discounted cash flow methodology), die im MIT-Bericht von 2009 beschrieben ist. • Technische Parameter der LIFE-Punkt-Designs (LIFE.1, LIFE.2, LIFE.3): o Die Kosten und die LCOE spiegeln die unterschiedlichen technischen Spezifikationen und Reifegrade dieser drei Designs wider. o LIFE.1 (erste ihrer Art, "first-of-a-kind") liegt am oberen Ende der Kostenbandbreite, da es maximal bestehende Materialien und Technologien nutzt und als Testbett dient. o LIFE.3 (reiferes System) liegt am unteren Ende der Kostenbandbreite und erfasst potenzielle Verbesserungen in der Zieleffizienz, niedrigere Fusionszielkosten und höhere Betriebstemperaturen. o Wichtige technische Parameter, die die Kosten beeinflussen, sind unter anderem die Laserenergie, die Wiederholungsrate, der elektrische Gewinn der Anlage, der thermisch-elektrische Wirkungsgrad, die Lebensdauer der ersten Wand, die Neutronenbelastung und die Fusionsleistung. • Sensitivität der Kosten: o Die Kosten des Strukturmaterials der Fusionskammer (insbesondere Oxid-Dispersions-gehärteter Stahl, ODS) sind der am stärksten gehebelte Wirtschaftsparameter. o Die Fusionszielkosten und die Zieleffizienz sind die nächstwichtigsten Parameter. | AM15: 1. Is the modeling approach transparently documented? -> Yes since: • Uses Discounted Cash Flow (DCF) per MIT (2009). • ~50 cost centers defined. • Laser costs: bottom-up (based on vendor quotes, NIF data). • Reactor/tritium/conversion costs: literature + scaling. • Target unit cost: internal target study. • O&M/incremental CapEx: % of total CapEx (based on MIT 2009). • Indirect costs: Gen IV guidelines. • Nuclear vs. conventional: General Atomics study. 2. Are model and cost assumptions from external sources or internally derived? • Mostly external, some adapted: o External: -> DCF: MIT (2009) -> Reactor/tritium/conversion: literature -> Target cost: LLNL target study -> O&M %: MIT (2009) -> Indirect cost multipliers: Gen IV -> Nuclear vs. conventional: GA study -> Comparison costs: Nicholson (2010) o Internal/Adjusted: -> Laser unit costs (vendor + NIF) -> Learning curves (laser)  -> Scaling of literature costs to LIFE specifications (literature: Nuclear Energy Cost Data Base, General electric report, studies from other icf reactor designs) 3. Were external sources modified? • Literature costs scaled to LIFE. • Laser costs adjusted via learning curves. • O&M % applied to LIFE CapEx (based on MIT). 4. Are uncertainties or sensitivities addressed? • Pre-conceptual design level → high uncertainty. • Monte Carlo sensitivity analysis (LCOE). • Sensitivities: o Fusion chamber material (ODS steel) o Target cost and gain o Market entry timing (2030 vs. 2040) o Cost of carbon (external variable) 5. Is the costing approach bottom-up, top-down, or hybrid? • Hybrid. • Laser system: bottom-up. • Reactor, tritium, conversion: scaled top-down from literature. 6. Are costs based on physical and technical parameters? • Defined by: o Laser energy & repetition (14.8 Hz) o Electrical efficiency (43–53%) o Net fusion power o Availability (50% LIFE.1, 92% LIFE.2/3) o Use of RAFMS (LIFE.1), ODS steel (LIFE.2/3) o Diode pumping (10–20% efficiency) o Modular design (enables uptime & cost spread) o Natural scaling: $/kW improves with size 7. What technical and economic assumptions are made? • Technical: o NIF-based laser & target tech o Diode lasers (10–20% eff.) o Availability: 50–92% o Target mass production o LIFE.1 = testbed • Economic: o CO2 cost = $100/ton o Discount rate = 5% o CapEx = $4–6B o O&M = % of CapEx o Learning curves (laser) o Early market entry crucial for benefits 8. Which technical parameters most affect cost? • Fusion chamber material (ODS steel) • Target cost & efficiency • Temperature (→ thermal efficiency) • Plant size (→ capital intensity) • Laser efficiency (diode-based) • Availability (higher = lower LCOE) • Repetition rate (fixed at 14.8 Hz) 9. Is the reactor concept aligned with state of the art? • Yes, builds on NIF tech. • Improvements for commercial use: o Modular lasers o Active cooling o Diode pumping o Target mass production o ODS steel testing in LIFE.1 • Requires significant further development. 10. Is it a planned or hypothetical concept? • Planned. • Three-point designs: LIFE.1 (demo), LIFE.2 (1 GWe), LIFE.3 (mature). • Pilot operation planned ~12 years from start. • Includes staged commercialization roadmap. 11. How current are assumptions? • Based on 2007–2010 data. • Key sources: MIT (2009), LLNL (2009), Gen IV (2007), GA (1987). 12. How robust vs. speculative are assumptions? • Robust: o NIF-based tech o Vendor-based laser costs o O&M from MIT o Gen IV guidelines • Speculative: o Pre-concept design = high uncertainty o Aggressive commercialization strategy o Future gains (ODS, target cost/gain) o 92% availability is ambitious o Target mass production not yet realized 13. Are cost components disaggregated? • Yes: o CapEx: $4–6B range o Laser: separate bottom-up o Reactor/tritium/conversion: scaled from literature o Targets: separate unit cost o O&M/CapEx: % of total o Indirect costs: separate (Gen IV) 14. Are material and component costs separately stated? • Materials: o Chamber structure is key economic driver o RAFMS (LIFE.1), ODS (LIFE.2/3) • Components: o Laser costs (vendor + NIF) o Reactor/tritium/conversion: from literature o Targets: separate unit cost 15. Strategic, economic, or technical focus? • All three, but strategic is dominant. o Quantifies CO2/waste/plutonium savings o Proposes commercialization path • Economic: LCOE analysis, cost comparison • Technical: NIF-based concept + upgrades needed 16. Is the study reactor-focused or energy-system oriented? • Energy-system oriented. o Fusion's role in decarbonizing US grid o Avoids carbon/waste/plutonium o Compares LCOE to other technologies o Assumes fusion displaces fossil/nuclear plants o Places LIFE in broader generation mix | AN15: 1. Ist der Modellierungsansatz transparent dokumentiert? Ja, der Modellierungsansatz ist transparent dokumentiert. Die Studie gibt an, dass die "Cost of electricity" (Stromgestehungskosten) unter Verwendung der Discounted Cash Flow (DCF) Methodik berechnet wurde, die im MIT-Bericht von 2009 beschrieben ist. Das LIFE-Kraftwerk ist in etwa 50 Kostenstellen unterteilt. Die Kosten für das Lasersystem wurden mittels einer Bottom-up-Methodik geschätzt, wobei die Stückkosten aus Lieferantenangeboten und Daten des NIF-Projekts abgeleitet wurden. Kosten für den Fusionsreaktor, die Tritiumanlage und die Stromumwandlungssysteme wurden aus Studien in der Literatur entnommen und unter Verwendung von Standard-Skalierungsbeziehungen auf den LIFE-Betriebspunkt skaliert. Die Stückkosten für Fusions-Targets wurden aus einer Studie zur Targetherstellung abgeleitet. Jährliche Betriebs-, Wartungs- und inkrementelle Kapitalkosten (Nicht-Brennstoff) wurden als Prozentsätze der Gesamtkapitalkosten der Anlage angenommen, wobei diese Prozentsätze aus der MIT-Publikation von 2009 zur Zukunft der Kernkraft stammen. Indirekte Kostenmultiplikatoren stammen aus den Gen IV-Kostenabschätzungsrichtlinien. Unterschiede bei den Kapital- und indirekten Kosten zwischen nuklearen und konventionellen Systemen und Strukturen wurden aus einer General Atomics-Studie entnommen. 2. Beruhen die Modell- und Kostenannahmen auf externen Quellen oder wurden sie selbst abgeleitet? Die Modell- und Kostenannahmen beruhen überwiegend auf externen Quellen, wurden aber teilweise selbst abgeleitet oder angepasst. o Externe Quellen:  DCF-Methodik: 2009 MIT-Bericht.  Kosten für Fusionsreaktor, Tritiumanlage, Stromumwandlungssysteme: Studien aus der Literatur.  Stückkosten für Fusions-Targets: Studie zur Targetherstellung.  Prozentsätze für O&M und inkrementelle Kapitalkosten: 2009 MIT-Publikation.  Indirekte Kostenmultiplikatoren: Gen IV-Kostenabschätzungsrichtlinien.  Kostenunterschiede nuklear vs. konventionell: General Atomics-Studie.  Kosten alternativer Technologien für den Vergleich: Eine Studie von Nicholson (2010). o Selbst abgeleitet/angepasst:  Stückkosten für Lasersysteme: Abgeleitet aus Lieferantenangeboten und NIF-Projektdaten.  Kostenreduktionen aufgrund von Fertigungslernkurven für Lasersysteme: Geschätzt basierend auf Erfahrungen mit NIF.  Skalierung von Kosten aus Literaturstudien auf den LIFE-Betriebspunkt: Mit "Standard-Skalierungsbeziehungen" angewendet. 3. Falls externe Quellen verwendet wurden – wurden diese modifiziert? Ja, die aus externen Quellen stammenden Kosten wurden modifiziert, indem sie auf den spezifischen LIFE-Betriebspunkt skaliert wurden. Für die Kosten des Lasersystems wurden zudem Kostenreduktionen aufgrund von Fertigungslernkurven angewendet, basierend auf Erfahrungen mit NIF. Die Prozentsätze für O&M wurden aus dem MIT-Bericht "abgeleitet" und auf die Gesamtkapitalkosten des LIFE-Kraftwerks angewendet, was eine Anpassung an das spezifische Projekt darstellt. 4. Werden Unsicherheiten oder Sensitivitäten thematisiert? Ja, Unsicherheiten und Sensitivitäten werden thematisiert. o Unsicherheiten: Die Studie weist explizit darauf hin, dass die LIFE-Kostenabschätzungen auf einem "pre-conceptual design level" basieren, was bedeutet, dass zusätzliche Arbeit erforderlich ist. Der gesamte Kommerzialisierungsansatz birgt "technisches Risiko" und wird als "aggressiv" bezeichnet. o Sensitivitäten:  Eine Monte-Carlo-Sensitivitätsanalyse der Stromgestehungskosten wurde durchgeführt und in Abbildung 5 dargestellt.  Als der wirtschaftlich am stärksten beeinflussende Parameter wurde das Strukturmaterial der Fusionskammer identifiziert. Dies unterstreicht die Bedeutung der laufenden Entwicklung von oxiddispersionsgehärtetem Stahl (ODS-Stahl).  Die nächstwichtigsten Parameter sind die Kosten der Fusions-Targets und deren Effizienz.  Die wirtschaftlichen Vorteile (z.B. vermiedene CO2-Emissionen) werden als sensitiv gegenüber dem Zeitpunkt des Markteintritts dargestellt; ein späterer Eintritt (z.B. 2040 statt 2030) reduziert die Vorteile erheblich.  Die Kosten der Stromerzeugung werden auch in Bezug auf die Kosten für CO2-Emissionen (Cost of Carbon) verglichen, was eine Sensitivität gegenüber diesem externen Faktor darstellt. 5. Wird offengelegt, ob die Kostenabschätzung auf einem Bottom-up-, Top-down- oder hybriden Ansatz basiert? Ja, es wird offengelegt, dass ein hybrider Ansatz verwendet wurde. o Die Kosten für das Lasersystem wurden mit einer Bottom-up-Methodik geschätzt. o Die Kosten für den Fusionsreaktor, die Tritiumanlage und die Stromumwandlungssysteme wurden aus bestehenden Studien in der Literatur entnommen und auf den LIFE-Betriebspunkt skaliert. Dies kann als eine Form der Top-down-Anwendung von externen Daten interpretiert werden. 6. Beruht die Kostenherleitung auf physikalischen und technologischen Werten? Ja, die Kostenherleitung beruht auf physikalischen und technologischen Werten. o Die drei LIFE-Punkt-Designs (LIFE.1, LIFE.2, LIFE.3) sind durch spezifische technische Parameter wie Laserenergie, Wiederholungsrate, thermisch-elektrische Effizienz, Fusionsleistung und Anlagenverfügbarkeit definiert, die direkt die Kosten beeinflussen. o Die Verwendung von fortschrittlichen Materialien wie ODS-Stahl ermöglicht höhere Betriebstemperaturen und Leistungsdichten, was als der "wirtschaftlich am stärksten beeinflussende Parameter" hervorgehoben wird. o Die Effizienz der Umwandlung von Laserenergie in Fusionsenergie steigt mit zunehmender elektrischer Leistung, was zu einer geringeren Kapitalintensität ($/kW) bei größeren Anlagen führt ("natürliche Skaleneffizienz"). o Die Notwendigkeit von Diodenpumpen für die Laser (statt Blitzlampen) wird genannt, um die für ein Kraftwerk erforderliche Lasereffizienz von ~10% bis 20% zu erreichen, was sich auf die Gesamteffizienz und die Kosten auswirkt. o Targetkosten und Targeteffizienz sind die nächstwichtigsten Hebel für die Wirtschaftlichkeit. o Eine hohe Anlagenverfügbarkeit (92% für spätere Designs) ist durch die modulare Architektur der Anlage ermöglicht und verteilt die Fixkosten auf eine größere Strommenge, was die Stromgestehungskosten senkt. 7. Welche technischen und wirtschaftlichen Annahmen wurden getroffen? Technische Annahmen: o Lasertechnologie: Nutzung der grundlegenden Lasertechnologie und Targetphysik der NIF (Neodym-dotierte Glas-Gain-Medien, Multipass-Architektur, räumliche Filterung, indirekt angesteuertes Hot-Spot-Zündungs-Fusionstarget). o Laser-Repetitionsrate: Konstante 14,8 Hz für alle LIFE-Konzepte. o Laser-Effizienz: Erreichung von 10% bis 20% Effizienz durch Diodenpumpen. o Wärme-zu-Strom-Effizienz: 43% (LIFE.1), 48% (LIFE.2), 53% (LIFE.3). o Anlagenverfügbarkeit (Kapazitätsfaktor): 50% für LIFE.1, 92% für LIFE.2 und LIFE.3 (als "10th of a kind plant" angenommen). o Materialien: Nutzung von RAFMS für LIFE.1 und ODS-Stahl für LIFE.2 und LIFE.3, um höhere Temperaturen und Leistungsdichten zu ermöglichen. o Targetproduktion: Fähigkeit zur Massenproduktion von Fusions-Targets. o Anlagenskalierung: Natürliche Skaleneffizienz, bei der die Kapitalintensität ($/kW) bei größeren Anlagen sinkt. o LIFE.1 als Testbett: Wird Materialien und Prozesse unter kontinuierlichem Fusionsbetrieb qualifizieren. Wirtschaftliche Annahmen: o CO2-Kosten: 100 $/MT für die Berechnung des Barwerts der vermiedenen Emissionen. o Diskontierungssatz: 5% für die Berechnung des Barwerts der vermiedenen Emissionen. o O&M- und inkrementelle Kapitalkosten: Skalieren als Prozentsätze der Gesamtkapitalkosten der Anlage. o Lernkurven: Kostenreduktionen aufgrund von Fertigungslernkurven für Lasersysteme. o Kapitalkosten-Range: Geschätzte Kapitalkosten für alle drei Systeme im Bereich von 4 bis 6 Milliarden US-Dollar. o Markteintritts-Timing: Quantifizierung der Vorteile für einen Markteintritt in den 2030er Jahren im Vergleich zu 2040. 8. Welche physikalischen und technischen Parameter beeinflussen die Kosten? Die Studie hebt hervor, dass folgende physikalische und technische Parameter die Kosten am stärksten beeinflussen: o Strukturmaterial der Fusionskammer: Der wichtigste ökonomische Hebel; insbesondere die Entwicklung von ODS-Stahl für hohe Temperaturen und Strahlungsresistenz. o Fusions-Targetkosten und Targeteffizienz: Die zweitwichtigsten Hebel für die Wirtschaftlichkeit. o Betriebstemperatur und thermisch-elektrische Effizienz: Höhere Temperaturen (ermöglicht durch ODS-Stahl) führen zu einer Steigerung der thermisch-elektrischen Effizienz und damit zu besseren Kosten. o Anlagenleistung/Skalierung: Größere elektrische Leistung führt zu einer besseren Skaleneffizienz und geringeren Kapitalintensität ($/kW). o Laser-Effizienz: Eine höhere Lasereffizienz (10-20% mit Diodenpumpen) ist für den Kraftwerksbetrieb unerlässlich und wirkt sich auf die Gesamteffizienz und die Kosten aus. o Anlagenverfügbarkeit (Kapazitätsfaktor): Eine hohe Verfügbarkeit (92% für reifere Designs) verteilt die Fixkosten über eine größere Stromproduktion und senkt so die Stromgestehungskosten. o Wiederholungsrate: Die konstante Wiederholungsrate von 14,8 Hz ist ein Designparameter, der die Gesamtfusionsleistung beeinflusst. 9. Ist das technische Reaktorkonzept konsistent mit dem Stand der Technik (state of the art)? Das LIFE-Konzept basiert auf und nutzt die wissenschaftlichen und technologischen Fortschritte, die auf der National Ignition Facility (NIF) demonstriert werden. Es verwendet die gleiche grundlegende Lasertechnologie und Targetphysik wie die NIF. Allerdings werden für den Kraftwerksbetrieb Änderungen an den NIF-Designs als notwendig erachtet, die über den damaligen "state of the art" der NIF hinausgehen, um eine kommerzielle Anlage zu ermöglichen: o Ein kompakterer, modularer Laserarchitektur-Aufbau für den Hochverfügbarkeitsbetrieb. o Aktives Wärmemanagement für höhere Wiederholungsraten (10 bis 20 Hz). o Diodenpumpen statt Blitzlampen für eine Lasereffizienz auf Kraftwerksniveau (~10% bis 20%). o Massenproduzierbare Fusions-Targets. o Die Qualifizierung von fortschrittlichen, strahlungsresistenten Strukturmaterialien (wie ODS-Stahl) unter kontinuierlichem Fusionsbetrieb ist ein zentraler Zweck von LIFE.1. Zusammenfassend lässt sich sagen, dass das Konzept im Wesentlichen mit dem damaligen Stand der Technik (NIF-Technologie) konsistent ist, jedoch erhebliche Weiterentwicklungen und Qualifizierungen erfordert, um für einen kommerziellen Dauerbetrieb geeignet zu sein. 10. Handelt es sich um ein geplantes Konzept oder um ein hypothetisches Design? Es handelt sich um ein geplantes Konzept mit einem vorgeschlagenen Kommerzialisierungspfad. Die Studie beschreibt diesen Pfad in Form von drei "Punkt-Designs": LIFE.1, LIFE.2 und LIFE.3. o LIFE.1 ist als Demonstrationsanlage konzipiert, die innerhalb von 10 bis 15 Jahren nach der Zündung auf der NIF betriebsbereit sein soll und dazu dient, die für ein kommerzielles Kraftwerk benötigten Prozesse und Materialien zu qualifizieren. o LIFE.2 ist als 1 GWe kommerzielles Kraftwerk konzipiert, und LIFE.3 stellt das Potenzial für eine ausgereifte LIFE-Technologie dar. o Es wird ein indikativer Zeitplan für Design und Bau präsentiert, der erste Pilotbetriebe in etwa 12 Jahren ab Projektstart vorsieht. Obwohl die Kostenabschätzungen auf einem "pre-conceptual design level" liegen und der Ansatz technische Risiken birgt, ist es klar ein strategischer Plan mit konkreten Phasen für die Entwicklung und den Bau von Fusionskraftwerken. 11. Wie aktuell sind die technischen und wirtschaftlichen Annahmen? Die Studie wurde im Juli 2011 veröffentlicht. Die technischen und wirtschaftlichen Annahmen basieren größtenteils auf Quellen aus den späten 2000er Jahren (2007-2010): o Kosten für alternative Technologien: Nicholson (2010). o DCF-Methodik, O&M-Prozentsätze: MIT-Bericht (2009). o Target-Fabrikationskosten: LLNL-Bericht (2009). o EIA-Prognosen für Energienachfrage (2009). o Gen IV Kostenrichtlinien (2007). o Einige grundlegende Kostendaten aus Literaturstudien reichen bis in die 1980er und 1990er Jahre zurück. Die "General Atomics study" für Kostenunterschiede zwischen nuklearem und konventionellem Standard stammt von 1987. Daher spiegeln die Annahmen den Stand der Technik und die wirtschaftlichen Bedingungen der frühen 2010er Jahre wider. 12. Wie belastbar oder spekulativ sind die getroffenen Annahmen? Die getroffenen Annahmen sind eine Mischung aus belastbaren und spekulativen Elementen: o Belastbar: Die Studie nutzt die auf der NIF demonstrierte Wissenschaft und Technologie als Grundlage. Die Kosten für Lasersysteme basieren auf Anbieterangeboten und Daten aus dem NIF-Projekt. O&M-Annahmen stammen aus einem etablierten MIT-Bericht zum Thema Kernkraft. Indirekte Kostenmultiplikatoren basieren auf anerkannten Gen IV-Richtlinien. Die Quantifizierung der vermiedenen Emissionen und Abfälle basiert auf klaren Szenarien. o Spekulativ:  Die Kostenabschätzungen liegen auf einem "pre-conceptual design level", was inhärent einen hohen Grad an Unsicherheit mit sich bringt und "zusätzliche Arbeit" erfordert.  Der Kommerzialisierungsansatz birgt "technische Risiken" und ist "aggressiv".  Annahmen für die reiferen Designs (LIFE.2 und LIFE.3) beinhalten erwartete Verbesserungen in Bereichen wie Targeteffizienz, niedrigere Targetkosten und höhere Betriebstemperaturen, sowie die Qualifizierung von fortschrittlichen Materialien (ODS-Stahl), die noch nicht vollständig für den Dauerbetrieb in einem Fusionskraftwerk bewiesen sind.  Die Annahme einer sehr hohen Verfügbarkeit von 92% für spätere Anlagen ist ein ehrgeiziges Ziel, das die Reife der Technologie und modulare Bauweise voraussetzt.  Die Massenproduktion von Fusions-Targets wird als zukünftiges Ziel genannt. Zusammenfassend lässt sich sagen, dass die Annahmen dort belastbar sind, wo sie auf bestehenden, experimentell demonstrierten Technologien (NIF) oder etablierten wirtschaftlichen Modellen basieren. Für die kommerziellen Phasen und die zukünftigen Potenziale sind sie jedoch naturgemäß spekulativer und bauen auf erwarteten technologischen Durchbrüchen und Optimierungen auf. 13. Werden die einzelnen Kostenkomponenten, wie z.B. O&M etc. separat ausgewiesen? Ja, die Hauptkostenkomponenten werden separat berücksichtigt und ausgewiesen, auch wenn keine detaillierte Auflistung aller 50 Kostenstellen in den vorliegenden Auszügen erfolgt. o Kapitalkosten: Geschätzt im Bereich von 4 bis 6 Milliarden US-Dollar für alle drei Systeme. o Lasersystemkosten: Separat mit einer Bottom-up-Methodik geschätzt. o Kosten für Fusionsreaktor, Tritiumanlage und Stromumwandlungssysteme: Separat aus Literaturstudien entnommen und skaliert. o Fusions-Target-Stückkosten: Separat aus einer Herstellungsstudie abgeleitet. o Jährliche Nicht-Brennstoff-Betriebs-, Wartungs- (O&M) und inkrementelle Kapitalkosten: Als Prozentsätze der Gesamtkapitalkosten angenommen. o Indirekte Kostenmultiplikatoren: Separat berücksichtigt. 14. Werden Materialkosten und Komponentenkosten separat ausgewiesen? o Materialkosten: Die Studie nennt das Strukturmaterial der Fusionskammer als den "wirtschaftlich am stärksten beeinflussenden Parameter". Dies unterstreicht die Bedeutung der Materialkosten für die Gesamtwirtschaftlichkeit, auch wenn spezifische absolute Zahlen nicht explizit aufgeführt sind. Es wird die Verwendung von RAFMS (für LIFE.1) und ODS-Stahl (für LIFE.2 und LIFE.3) als First-Wall-Materialien genannt. o Komponentenkosten: Ja, Komponentenkosten werden für wichtige Systeme separat behandelt:  Lasersystemkosten: Basieren auf Stückkosten aus Anbieterangeboten und NIF-Daten.  Kosten für Fusionsreaktor, Tritiumanlage und Stromumwandlungssysteme: Werden aus Literaturstudien entnommen.  Fusions-Target-Stückkosten: Sind ein explizit separater Posten. Die Studie konzentriert sich auf die Aggregation dieser Komponenten zu den Gesamtkapitalkosten und zur Stromgestehungskosten. 15. Liegt der Fokus der Studie auf technischen, ökonomischen oder strategischen Fragestellungen? Die Studie hat einen starken strategischen Fokus, der durch detaillierte ökonomische Analysen und eine Beschreibung des technischen Konzepts und der erforderlichen Fortschritte untermauert wird. o Strategisch: Der Titel "LIFE: The Case for Early Commercialization of Fusion Energy" zeigt den primären Zweck. Es wird der "Nutzen eines Fusionsenergie-Option in einem relevanten Zeitrahmen" bewertet, die Vorteile einer "frühen Kommerzialisierung" (bezüglich CO2-Vermeidung, Atommüll und Plutonium) quantifiziert und ein "Kommerzialisierungspfad" vorgeschlagen. Es wird betont, dass ein "nationales Engagement" erforderlich ist. o Ökonomisch: Ein Abschnitt ist explizit den "LIFE Economics" gewidmet. Die Studie schätzt Kapitalkosten und Stromgestehungskosten ab und vergleicht sie mit anderen kohlenstoffarmen Technologien. Es wird eine Sensitivitätsanalyse der Stromgestehungskosten durchgeführt. o Technisch: Das LIFE-Konzept selbst wird beschrieben, seine Beziehung zur NIF-Technologie erläutert und die technischen Änderungen und Risikoreduzierungsaktivitäten für den Kraftwerksbetrieb aufgeführt. 16. Bezieht sich die Studie auf ein Energiesystem (z. B. Integration, Vergleich mit anderen Technologien) oder ist sie rein reaktorbezogen? Die Studie ist nicht rein reaktorbezogen, sondern bezieht sich explizit auf das breitere Energiesystem. o Sie bewertet die Vorteile der Fusionsenergie im Kontext des US-Stromerzeugungssystems in Bezug auf die Vermeidung von Kohlenstoffemissionen, Nuklearabfällen und Plutoniumproduktion. o Die Notwendigkeit des Baus vieler neuer GW-Klasse-Kraftwerke bis 2100 zur Rekapitalisierung des Stromnetzes wird hervorgehoben. o Die Vorteile werden quantifiziert, indem angenommen wird, dass Fusionskraftwerke andere Kraftwerkstypen (z.B. Kohlekraftwerke, Leichtwasserreaktoren, schnelle Reaktoren) verdrängen. o Die Stromgestehungskosten von LIFE werden direkt mit denen anderer kohlenstoffarmer Energietechnologien verglichen, was eine systemweite Perspektive einnimmt. | AR15: Generomak - ESECOM | AS15: 1200 | AT15: 60500000 | AU15: USD | AV15: 1986 | AW15: Delene et al (1988) | AX15: Secondary ref Woodruff et al (2016)
A16: 561 | B16: Tokamak (Fusion-Fission Hybrid) | C16: Magnetic | D16: Tokamak | E16: 1000 | F16: Capital Cost | G16: NOAK | H16: Absolute | I16: 4645000000 | J16: USD | K16: 2011 | L16: Yamazaki et al. (2011) | O16: Lifetime 30 years | P16: 0.75 | Q16: - | R16: - | S16: - | T16: - | AR16: ARIES-1 | AS16: 1000 | AT16: 43000000 | AU16: USD | AV16: 1980 | AW16: Wittenberg (1991) | AX16: Secondary ref Woodruff et al (2016)
A17: 566 | B17: Tokamak (D-3He) | C17: Magnetic | D17: Tokamak | E17: 1000 | F17: Capital Cost | G17: NOAK | H17: Absolute | I17: 5227000000 | J17: USD | K17: 2011 | L17: Yamazaki et al. (2011) | O17: Lifetime 30 years | P17: 0.75 | Q17: - | R17: - | S17: - | T17: - | AE17: or advanced 10th-OAK, not specified | AR17: ESECOM-He/Li2O | AS17: 1200 | AT17: 58000000 | AU17: USD | AV17: 1980 | AW17: Wittenberg (1991) | AX17: Secondary ref Woodruff et al (2016)
